decode_execute/riscv_defines.vh

//opcode macros
//funct3 macros
//funct7 macros
//ALU operation macros
//writeback select macros
//immediate type macros
//FFT custom instruction macros
`ifndef RISCV_DEFINES_VH
`define RISCV_DEFINES_VH

// ============================================================
// Basic architectural parameters
// ============================================================
`define XLEN           32
`define REG_ADDR_W     5
`define INSTR_W        32
`define DATA_W         32
`define IMEM_DEPTH     1024
`define DMEM_DEPTH     1024
`define RESET_PC             0
// ============================================================
// RV32I opcodes
// ============================================================
`define OPCODE_OP      7'b0110011   // R-type
`define OPCODE_OP_IMM  7'b0010011   // I-type ALU
`define OPCODE_LOAD    7'b0000011   // LW
`define OPCODE_STORE   7'b0100011   // SW
`define OPCODE_BRANCH  7'b1100011   // BEQ/BNE
`define OPCODE_JAL     7'b1101111   // JAL

// ============================================================
// Custom opcode space for FFT instruction
// custom-0 opcode
// ============================================================
`define OPCODE_FFT     7'b0001011

// ============================================================
// funct3 values
// ============================================================
`define FUNCT3_ADD_SUB 3'b000
`define FUNCT3_XOR     3'b100
`define FUNCT3_OR      3'b110
`define FUNCT3_AND     3'b111

`define FUNCT3_ADDI    3'b000

`define FUNCT3_LW      3'b010
`define FUNCT3_SW      3'b010

`define FUNCT3_BEQ     3'b000
`define FUNCT3_BNE     3'b001

// ============================================================
// funct7 values
// ============================================================
`define FUNCT7_ADD     7'b0000000
`define FUNCT7_SUB     7'b0100000
`define FUNCT7_LOGIC   7'b0000000

// ============================================================
// FFT custom instruction fields
// Example: FFT_BLY rd, rs1, rs2
// ============================================================
`define FUNCT3_FFT_BLY 3'b000
`define FUNCT7_FFT_BLY 7'b0000001

// ============================================================
// ALU operation select
// ============================================================
`define ALU_ADD        4'd0
`define ALU_SUB        4'd1
`define ALU_AND        4'd2
`define ALU_OR         4'd3
`define ALU_XOR        4'd4
`define ALU_PASS       4'd5

// ============================================================
// Writeback select
// ============================================================
`define WB_ALU         2'd0
`define WB_MEM         2'd1
`define WB_PC4         2'd2
`define WB_FFT         2'd3

// ============================================================
// Immediate type select
// ============================================================
`define IMM_I          3'd0
`define IMM_S          3'd1
`define IMM_B          3'd2
`define IMM_J          3'd3
`define IMM_NONE       3'd4

`endif

decode_execute/alu.v
`include "riscv_defines.vh"

/*
------------------------------------------------------------------------------
File        : alu.v
Module      : alu
Purpose     : Arithmetic Logic Unit for baseline RV32I datapath

Functionality:
- Performs basic arithmetic and logical operations
- Used by processor execute stage for ALU instructions, address generation,
  and simple datapath pass-through operations

Supported operations:
- ALU_ADD  : a + b
- ALU_SUB  : a - b
- ALU_AND  : a & b
- ALU_OR   : a | b
- ALU_XOR  : a ^ b
- ALU_PASS : result = b

Major inputs:
- a        : Operand A (`XLEN bits)
- b        : Operand B (`XLEN bits)
- alu_op   : ALU operation select

Major outputs:
- result   : ALU result (`XLEN bits)
- zero     : Asserted when result is all zeros

Notes:
- Pure combinational logic
- zero flag can be used by branch/equality logic
- Written in Verilog-only style for Icarus compatibility
------------------------------------------------------------------------------
*/

module alu (
    input  [`XLEN-1:0] a,
    input  [`XLEN-1:0] b,
    input  [3:0]       alu_op,
    output reg [`XLEN-1:0] result,
    output             zero
);

always @(*) begin
    case (alu_op)
        `ALU_ADD:  result = a + b;
        `ALU_SUB:  result = a - b;
        `ALU_AND:  result = a & b;
        `ALU_OR:   result = a | b;
        `ALU_XOR:  result = a ^ b;
        `ALU_PASS: result = b;
        default:   result = {`XLEN{1'b0}};
    endcase
end

assign zero = (result == {`XLEN{1'b0}});

endmodule

decode_execute/tb_alu.v
`timescale 1ns/1ps
`include "riscv_defines.vh"

module tb_alu;

    reg  [`XLEN-1:0] a;
    reg  [`XLEN-1:0] b;
    reg  [3:0]       alu_op;

    wire [`XLEN-1:0] result;
    wire             zero;

    integer errors;

    alu uut (
        .a      (a),
        .b      (b),
        .alu_op (alu_op),
        .result (result),
        .zero   (zero)
    );

    task check_result;
        input [`XLEN-1:0] expected_result;
        input             expected_zero;
        input [127:0]     test_name;
        begin
            #1;
            if ((result !== expected_result) || (zero !== expected_zero)) begin
                $display("FAIL : %s", test_name);
                $display("       a=%h b=%h alu_op=%h", a, b, alu_op);
                $display("       expected result=%h zero=%b", expected_result, expected_zero);
                $display("       got      result=%h zero=%b", result, zero);
                errors = errors + 1;
            end
            else begin
                $display("PASS : %s  result=%h zero=%b", test_name, result, zero);
            end
        end
    endtask

    initial begin
        $dumpfile("tb_alu.vcd");
        $dumpvars(0, tb_alu);

        errors = 0;

        // ADD
        a = 32'd10; b = 32'd5; alu_op = `ALU_ADD;
        check_result(32'd15, 1'b0, "ADD_10_5");

        // SUB
        a = 32'd10; b = 32'd5; alu_op = `ALU_SUB;
        check_result(32'd5, 1'b0, "SUB_10_5");

        // SUB => ZERO
        a = 32'd25; b = 32'd25; alu_op = `ALU_SUB;
        check_result(32'd0, 1'b1, "SUB_ZERO");

        // AND
        a = 32'hF0F0_F0F0; b = 32'h0FF0_00FF; alu_op = `ALU_AND;
        check_result(32'h00F0_00F0, 1'b0, "AND_TEST");

        // OR
        a = 32'hF0F0_0000; b = 32'h0FF0_00FF; alu_op = `ALU_OR;
        check_result(32'hFFF0_00FF, 1'b0, "OR_TEST");

        // XOR
        a = 32'hAAAA_5555; b = 32'hFFFF_0000; alu_op = `ALU_XOR;
        check_result(32'h5555_5555, 1'b0, "XOR_TEST");

        // PASS
        a = 32'h1234_5678; b = 32'hDEAD_BEEF; alu_op = `ALU_PASS;
        check_result(32'hDEAD_BEEF, 1'b0, "PASS_TEST");

        // ADD wraparound
        a = 32'hFFFF_FFFF; b = 32'h0000_0001; alu_op = `ALU_ADD;
        check_result(32'h0000_0000, 1'b1, "ADD_WRAP");

        if (errors == 0)
            $display("\nALL ALU TESTS PASSED\n");
        else
            $display("\nALU TESTS FAILED : total errors = %0d\n", errors);

        $finish;
    end

endmodule

decode_execute/tb_alu.vcd
$date
	Sun May 03 19:48:11 2026
$end
$version
	Icarus Verilog
$end
$timescale
	1ps
$end
$scope module tb_alu $end
$var wire 1 ! zero $end
$var wire 32 " result [31:0] $end
$var reg 32 # a [31:0] $end
$var reg 4 $ alu_op [3:0] $end
$var reg 32 % b [31:0] $end
$var integer 32 & errors [31:0] $end
$scope module uut $end
$var wire 32 ' a [31:0] $end
$var wire 4 ( alu_op [3:0] $end
$var wire 32 ) b [31:0] $end
$var wire 1 ! zero $end
$var reg 32 * result [31:0] $end
$upscope $end
$scope task check_result $end
$var reg 32 + expected_result [31:0] $end
$var reg 1 , expected_zero $end
$var reg 128 - test_name [127:0] $end
$upscope $end
$upscope $end
$enddefinitions $end
$comment Show the parameter values. $end
$dumpall
$end
#0
$dumpvars
b100000101000100010001000101111100110001001100000101111100110101 -
0,
b1111 +
b1111 *
b101 )
b0 (
b1010 '
b0 &
b101 %
b0 $
b1010 #
b1111 "
0!
$end
#1000
b101 "
b101 *
b101001101010101010000100101111100110001001100000101111100110101 -
b101 +
b1 $
b1 (
#2000
1!
b0 "
b0 *
b101001101010101010000100101111101011010010001010101001001001111 -
1,
b0 +
b11001 %
b11001 )
b11001 #
b11001 '
#3000
0!
b111100000000000011110000 "
b111100000000000011110000 *
b100000101001110010001000101111101010100010001010101001101010100 -
0,
b111100000000000011110000 +
b10 $
b10 (
b1111111100000000000011111111 %
b1111111100000000000011111111 )
b11110000111100001111000011110000 #
b11110000111100001111000011110000 '
#4000
b11111111111100000000000011111111 "
b11111111111100000000000011111111 *
b1001111010100100101111101010100010001010101001101010100 -
b11111111111100000000000011111111 +
b11 $
b11 (
b11110000111100000000000000000000 #
b11110000111100000000000000000000 '
#5000
b1010101010101010101010101010101 "
b1010101010101010101010101010101 *
b101100001001111010100100101111101010100010001010101001101010100 -
b1010101010101010101010101010101 +
b100 $
b100 (
b11111111111111110000000000000000 %
b11111111111111110000000000000000 )
b10101010101010100101010101010101 #
b10101010101010100101010101010101 '
#6000
b11011110101011011011111011101111 "
b11011110101011011011111011101111 *
b10100000100000101010011010100110101111101010100010001010101001101010100 -
b11011110101011011011111011101111 +
b101 $
b101 (
b11011110101011011011111011101111 %
b11011110101011011011111011101111 )
b10010001101000101011001111000 #
b10010001101000101011001111000 '
#7000
1!
b0 "
b0 *
b100000101000100010001000101111101010111010100100100000101010000 -
1,
b0 +
b0 $
b0 (
b1 %
b1 )
b11111111111111111111111111111111 #
b11111111111111111111111111111111 '
