decode_execute/control_unit.v
/*
------------------------------------------------------------------------------
File        : control_unit.v
Module      : control_unit
Purpose     : Main decoder + ALU decoder for 3-stage RV32I pipeline
Supported   : ADD, SUB, AND, OR, XOR, LW, SW, BEQ, BNE, JAL, FFTBLY

Decode style:
- Combinational control generation
- Defaults assigned first to avoid latches
- ALU control generated directly from opcode/funct fields
- Custom FFT instruction recognized using:
    opcode = 7'h3B
    funct3 = 3'b000
    funct7 = 7'h01

Outputs:
- reg_write   : register file write enable
- mem_read    : data memory read enable
- mem_write   : data memory write enable
- mem_to_reg  : WB mux select, 1 => memory data, 0 => exec result
- alu_src     : ALU input-B select, 1 => immediate, 0 => rs2 data
- alu_ctrl    : operation code to ALU
- branch      : branch-class instruction present
- branch_ne   : 0 => BEQ, 1 => BNE
- jump        : jump-class instruction present
- fft_en      : select custom FFT datapath in execute stage
- valid_instr : high when opcode/funct combination is supported

Suggested ALU control encoding:
- 4'b0000 : ADD
- 4'b0001 : SUB
- 4'b0010 : AND
- 4'b0011 : OR
- 4'b0100 : XOR
- 4'b0101 : PASS_B   (useful for future ops if needed)
------------------------------------------------------------------------------
*/

module control_unit (
    input  [6:0] opcode,
    input  [2:0] funct3,
    input  [6:0] funct7,

    output reg       reg_write,
    output reg       mem_read,
    output reg       mem_write,
    output reg       mem_to_reg,
    output reg       alu_src,
    output reg [3:0] alu_ctrl,
    output reg       branch,
    output reg       branch_ne,
    output reg       jump,
    output reg       fft_en,
    output reg       valid_instr
);

    // ------------------------------------------------------------------------
    // Opcode localparams
    // ------------------------------------------------------------------------
    localparam [6:0] OPCODE_RTYPE   = 7'b0110011;
    localparam [6:0] OPCODE_LOAD    = 7'b0000011; // LW
    localparam [6:0] OPCODE_STORE   = 7'b0100011; // SW
    localparam [6:0] OPCODE_BRANCH  = 7'b1100011; // BEQ/BNE
    localparam [6:0] OPCODE_JAL     = 7'b1101111; // JAL
    localparam [6:0] OPCODE_FFT     = 7'b0111011; // custom opcode 0x3B

    // ------------------------------------------------------------------------
    // ALU control localparams
    // ------------------------------------------------------------------------
    localparam [3:0] ALU_ADD    = 4'b0000;
    localparam [3:0] ALU_SUB    = 4'b0001;
    localparam [3:0] ALU_AND    = 4'b0010;
    localparam [3:0] ALU_OR     = 4'b0011;
    localparam [3:0] ALU_XOR    = 4'b0100;
    localparam [3:0] ALU_PASS_B = 4'b0101;

    always @(*) begin
        // --------------------------------------------------------------------
        // Safe defaults
        // --------------------------------------------------------------------
        reg_write   = 1'b0;
        mem_read    = 1'b0;
        mem_write   = 1'b0;
        mem_to_reg  = 1'b0;
        alu_src     = 1'b0;
        alu_ctrl    = ALU_ADD;
        branch      = 1'b0;
        branch_ne   = 1'b0;
        jump        = 1'b0;
        fft_en      = 1'b0;
        valid_instr = 1'b0;

        case (opcode)

            // ----------------------------------------------------------------
            // R-type ALU: ADD, SUB, AND, OR, XOR
            // ----------------------------------------------------------------
            OPCODE_RTYPE: begin
                reg_write   = 1'b1;
                mem_read    = 1'b0;
                mem_write   = 1'b0;
                mem_to_reg  = 1'b0;
                alu_src     = 1'b0;
                branch      = 1'b0;
                jump        = 1'b0;
                fft_en      = 1'b0;

                case ({funct7, funct3})
                    10'b0000000_000: begin
                        alu_ctrl    = ALU_ADD;
                        valid_instr = 1'b1;
                    end

                    10'b0100000_000: begin
                        alu_ctrl    = ALU_SUB;
                        valid_instr = 1'b1;
                    end

                    10'b0000000_111: begin
                        alu_ctrl    = ALU_AND;
                        valid_instr = 1'b1;
                    end

                    10'b0000000_110: begin
                        alu_ctrl    = ALU_OR;
                        valid_instr = 1'b1;
                    end

                    10'b0000000_100: begin
                        alu_ctrl    = ALU_XOR;
                        valid_instr = 1'b1;
                    end

                    default: begin
                        reg_write   = 1'b0;
                        valid_instr = 1'b0;
                    end
                endcase
            end

            // ----------------------------------------------------------------
            // Load: LW
            // ----------------------------------------------------------------
            OPCODE_LOAD: begin
                if (funct3 == 3'b010) begin
                    reg_write   = 1'b1;
                    mem_read    = 1'b1;
                    mem_write   = 1'b0;
                    mem_to_reg  = 1'b1;
                    alu_src     = 1'b1;
                    alu_ctrl    = ALU_ADD; // address = rs1 + imm
                    branch      = 1'b0;
                    jump        = 1'b0;
                    fft_en      = 1'b0;
                    valid_instr = 1'b1;
                end
            end

            // ----------------------------------------------------------------
            // Store: SW
            // ----------------------------------------------------------------
            OPCODE_STORE: begin
                if (funct3 == 3'b010) begin
                    reg_write   = 1'b0;
                    mem_read    = 1'b0;
                    mem_write   = 1'b1;
                    mem_to_reg  = 1'b0;
                    alu_src     = 1'b1;
                    alu_ctrl    = ALU_ADD; // address = rs1 + imm
                    branch      = 1'b0;
                    jump        = 1'b0;
                    fft_en      = 1'b0;
                    valid_instr = 1'b1;
                end
            end

            // ----------------------------------------------------------------
            // Branch: BEQ, BNE
            // Compare done via ALU subtract
            // ----------------------------------------------------------------
            OPCODE_BRANCH: begin
                case (funct3)
                    3'b000: begin // BEQ
                        reg_write   = 1'b0;
                        mem_read    = 1'b0;
                        mem_write   = 1'b0;
                        mem_to_reg  = 1'b0;
                        alu_src     = 1'b0;
                        alu_ctrl    = ALU_SUB;
                        branch      = 1'b1;
                        branch_ne   = 1'b0;
                        jump        = 1'b0;
                        fft_en      = 1'b0;
                        valid_instr = 1'b1;
                    end

                    3'b001: begin // BNE
                        reg_write   = 1'b0;
                        mem_read    = 1'b0;
                        mem_write   = 1'b0;
                        mem_to_reg  = 1'b0;
                        alu_src     = 1'b0;
                        alu_ctrl    = ALU_SUB;
                        branch      = 1'b1;
                        branch_ne   = 1'b1;
                        jump        = 1'b0;
                        fft_en      = 1'b0;
                        valid_instr = 1'b1;
                    end

                    default: begin
                        valid_instr = 1'b0;
                    end
                endcase
            end

            // ----------------------------------------------------------------
            // JAL
            // Write PC+4 into rd, next PC handled by branch/jump logic elsewhere
            // ALU control is not critical here, kept benign
            // ----------------------------------------------------------------
            OPCODE_JAL: begin
                reg_write   = 1'b1;
                mem_read    = 1'b0;
                mem_write   = 1'b0;
                mem_to_reg  = 1'b0;
                alu_src     = 1'b0;
                alu_ctrl    = ALU_ADD;
                branch      = 1'b0;
                jump        = 1'b1;
                fft_en      = 1'b0;
                valid_instr = 1'b1;
            end

            // ----------------------------------------------------------------
            // Custom FFT instruction
            // FFTBLY rd, rs1, rs2
            // funct7 = 7'h01, funct3 = 3'b000, opcode = 7'h3B
            // ----------------------------------------------------------------
            OPCODE_FFT: begin
                if ((funct7 == 7'h01) && (funct3 == 3'b000)) begin
                    reg_write   = 1'b1;
                    mem_read    = 1'b0;
                    mem_write   = 1'b0;
                    mem_to_reg  = 1'b0;
                    alu_src     = 1'b0;
                    alu_ctrl    = ALU_ADD; // ignored when fft_en=1
                    branch      = 1'b0;
                    jump        = 1'b0;
                    fft_en      = 1'b1;
                    valid_instr = 1'b1;
                end
            end

            default: begin
                reg_write   = 1'b0;
                mem_read    = 1'b0;
                mem_write   = 1'b0;
                mem_to_reg  = 1'b0;
                alu_src     = 1'b0;
                alu_ctrl    = ALU_ADD;
                branch      = 1'b0;
                branch_ne   = 1'b0;
                jump        = 1'b0;
                fft_en      = 1'b0;
                valid_instr = 1'b0;
            end
        endcase
    end

endmodule

decode_execute/tb_control_unit.v
`timescale 1ns/1ps
//iverilog -o cu_tb control_unit.v tb_control_unit.v
//vvp cu_tb
//gtkwave tb_control_unit.vcd

module tb_control_unit;

    reg  [6:0] opcode;
    reg  [2:0] funct3;
    reg  [6:0] funct7;

    wire       reg_write;
    wire       mem_read;
    wire       mem_write;
    wire       mem_to_reg;
    wire       alu_src;
    wire [3:0] alu_ctrl;
    wire       branch;
    wire       branch_ne;
    wire       jump;
    wire       fft_en;
    wire       valid_instr;

    integer errors;

    control_unit uut (
        .opcode     (opcode),
        .funct3     (funct3),
        .funct7     (funct7),
        .reg_write  (reg_write),
        .mem_read   (mem_read),
        .mem_write  (mem_write),
        .mem_to_reg (mem_to_reg),
        .alu_src    (alu_src),
        .alu_ctrl   (alu_ctrl),
        .branch     (branch),
        .branch_ne  (branch_ne),
        .jump       (jump),
        .fft_en     (fft_en),
        .valid_instr (valid_instr)
    );

    task check;
        input exp_reg_write;
        input exp_mem_read;
        input exp_mem_write;
        input exp_mem_to_reg;
        input exp_alu_src;
        input [3:0] exp_alu_ctrl;
        input exp_branch;
        input exp_branch_ne;
        input exp_jump;
        input exp_fft_en;
        input exp_valid;
        input [127:0] name;
        begin
            #1;
            if ((reg_write   !== exp_reg_write) ||
                (mem_read    !== exp_mem_read)  ||
                (mem_write   !== exp_mem_write) ||
                (mem_to_reg  !== exp_mem_to_reg)||
                (alu_src     !== exp_alu_src)   ||
                (alu_ctrl    !== exp_alu_ctrl)  ||
                (branch      !== exp_branch)    ||
                (branch_ne   !== exp_branch_ne) ||
                (jump        !== exp_jump)      ||
                (fft_en      !== exp_fft_en)    ||
                (valid_instr !== exp_valid)) begin
                $display("FAIL : %s", name);
                $display("  opcode=%b funct3=%b funct7=%b", opcode, funct3, funct7);
                $display("  got: rw=%b mr=%b mw=%b m2r=%b as=%b alu=%b br=%b bne=%b j=%b fft=%b val=%b",
                         reg_write, mem_read, mem_write, mem_to_reg, alu_src, alu_ctrl, branch, branch_ne, jump, fft_en, valid_instr);
                errors = errors + 1;
            end else begin
                $display("PASS : %s", name);
            end
        end
    endtask

    initial begin
        $dumpfile("tb_control_unit.vcd");
        $dumpvars(0, tb_control_unit);

        errors = 0;
        opcode = 7'b0000000;
        funct3 = 3'b000;
        funct7 = 7'b0000000;

        opcode = 7'b0110011; funct3 = 3'b000; funct7 = 7'b0000000;
        check(1,0,0,0,0,4'b0000,0,0,0,0,1, "R-type ADD");

        opcode = 7'b0110011; funct3 = 3'b000; funct7 = 7'b0100000;
        check(1,0,0,0,0,4'b0001,0,0,0,0,1, "R-type SUB");

        opcode = 7'b0110011; funct3 = 3'b111; funct7 = 7'b0000000;
        check(1,0,0,0,0,4'b0010,0,0,0,0,1, "R-type AND");

        opcode = 7'b0110011; funct3 = 3'b110; funct7 = 7'b0000000;
        check(1,0,0,0,0,4'b0011,0,0,0,0,1, "R-type OR");

        opcode = 7'b0110011; funct3 = 3'b100; funct7 = 7'b0000000;
        check(1,0,0,0,0,4'b0100,0,0,0,0,1, "R-type XOR");

        opcode = 7'b0000011; funct3 = 3'b010; funct7 = 7'b0000000;
        check(1,1,0,1,1,4'b0000,0,0,0,0,1, "LW");

        opcode = 7'b0100011; funct3 = 3'b010; funct7 = 7'b0000000;
        check(0,0,1,0,1,4'b0000,0,0,0,0,1, "SW");

        opcode = 7'b1100011; funct3 = 3'b000; funct7 = 7'b0000000;
        check(0,0,0,0,0,4'b0001,1,0,0,0,1, "BEQ");

        opcode = 7'b1100011; funct3 = 3'b001; funct7 = 7'b0000000;
        check(0,0,0,0,0,4'b0001,1,1,0,0,1, "BNE");

        opcode = 7'b1101111; funct3 = 3'b000; funct7 = 7'b0000000;
        check(1,0,0,0,0,4'b0000,0,0,1,0,1, "JAL");

        opcode = 7'b0111011; funct3 = 3'b000; funct7 = 7'h01;
        check(1,0,0,0,0,4'b0000,0,0,0,1,1, "Custom FFT");

        opcode = 7'b0111011; funct3 = 3'b001; funct7 = 7'h01;
        check(0,0,0,0,0,4'b0000,0,0,0,0,0, "Invalid FFT funct3");

        opcode = 7'b1111111; funct3 = 3'b000; funct7 = 7'b0000000;
        check(0,0,0,0,0,4'b0000,0,0,0,0,0, "Unknown opcode");

        if (errors == 0)
            $display("ALL TESTS PASSED");
        else
            $display("TOTAL ERRORS = %0d", errors);

        $finish;
    end

endmodule

decode_execute/tb_control_unit.vcd
$date
	Sat May 02 16:07:40 2026
$end
$version
	Icarus Verilog
$end
$timescale
	1ps
$end
$scope module tb_control_unit $end
$var wire 1 ! valid_instr $end
$var wire 1 " reg_write $end
$var wire 1 # mem_write $end
$var wire 1 $ mem_to_reg $end
$var wire 1 % mem_read $end
$var wire 1 & jump $end
$var wire 1 ' fft_en $end
$var wire 1 ( branch_ne $end
$var wire 1 ) branch $end
$var wire 1 * alu_src $end
$var wire 4 + alu_ctrl [3:0] $end
$var reg 3 , funct3 [2:0] $end
$var reg 7 - funct7 [6:0] $end
$var reg 7 . opcode [6:0] $end
$var integer 32 / errors [31:0] $end
$scope module uut $end
$var wire 3 0 funct3 [2:0] $end
$var wire 7 1 funct7 [6:0] $end
$var wire 7 2 opcode [6:0] $end
$var parameter 4 3 ALU_ADD $end
$var parameter 4 4 ALU_AND $end
$var parameter 4 5 ALU_OR $end
$var parameter 4 6 ALU_PASS_B $end
$var parameter 4 7 ALU_SUB $end
$var parameter 4 8 ALU_XOR $end
$var parameter 7 9 OPCODE_BRANCH $end
$var parameter 7 : OPCODE_FFT $end
$var parameter 7 ; OPCODE_JAL $end
$var parameter 7 < OPCODE_LOAD $end
$var parameter 7 = OPCODE_RTYPE $end
$var parameter 7 > OPCODE_STORE $end
$var reg 4 ? alu_ctrl [3:0] $end
$var reg 1 * alu_src $end
$var reg 1 ) branch $end
$var reg 1 ( branch_ne $end
$var reg 1 ' fft_en $end
$var reg 1 & jump $end
$var reg 1 % mem_read $end
$var reg 1 $ mem_to_reg $end
$var reg 1 # mem_write $end
$var reg 1 " reg_write $end
$var reg 1 ! valid_instr $end
$upscope $end
$scope task check $end
$var reg 4 @ exp_alu_ctrl [3:0] $end
$var reg 1 A exp_alu_src $end
$var reg 1 B exp_branch $end
$var reg 1 C exp_branch_ne $end
$var reg 1 D exp_fft_en $end
$var reg 1 E exp_jump $end
$var reg 1 F exp_mem_read $end
$var reg 1 G exp_mem_to_reg $end
$var reg 1 H exp_mem_write $end
$var reg 1 I exp_reg_write $end
$var reg 1 J exp_valid $end
$var reg 128 K name [127:0] $end
$upscope $end
$upscope $end
$enddefinitions $end
$comment Show the parameter values. $end
$dumpall
b100011 >
b110011 =
b11 <
b1101111 ;
b111011 :
b1100011 9
b100 8
b1 7
b101 6
b11 5
b10 4
b0 3
$end
#0
$dumpvars
b1010010001011010111010001111001011100000110010100100000010000010100010001000100 K
1J
1I
0H
0G
0F
0E
0D
0C
0B
0A
b0 @
b0 ?
b110011 2
b0 1
b0 0
b0 /
b110011 .
b0 -
b0 ,
b0 +
0*
0)
0(
0'
0&
0%
0$
0#
1"
1!
$end
#1000
b1 +
b1 ?
1!
1"
b1010010001011010111010001111001011100000110010100100000010100110101010101000010 K
b1 @
b100000 -
b100000 1
#2000
1!
b10 +
b10 ?
1"
b1010010001011010111010001111001011100000110010100100000010000010100111001000100 K
b10 @
b0 -
b0 1
b111 ,
b111 0
#3000
1!
b11 +
b11 ?
1"
b10100100010110101110100011110010111000001100101001000000100111101010010 K
b11 @
b110 ,
b110 0
#4000
1!
b100 +
b100 ?
1"
b1010010001011010111010001111001011100000110010100100000010110000100111101010010 K
b100 @
b100 ,
b100 0
#5000
1*
1$
1%
1!
b0 +
b0 ?
1"
b100110001010111 K
b0 @
1A
1G
1F
b10 ,
b10 0
b11 .
b11 2
#6000
1#
1!
1*
0$
0%
0"
b101001101010111 K
0G
1H
0F
0I
b100011 .
b100011 2
#7000
1)
b1 +
b1 ?
1!
0*
0#
b10000100100010101010001 K
1B
b1 @
0A
0H
b0 ,
b0 0
b1100011 .
b1100011 2
#8000
1(
1!
1)
b1 +
b1 ?
b10000100100111001000101 K
1C
b1 ,
b1 0
#9000
1&
1"
1!
0(
0)
b0 +
b0 ?
b10010100100000101001100 K
1E
0C
0B
b0 @
1I
b0 ,
b0 0
b1101111 .
b1101111 2
#10000
1'
1!
0&
1"
b1000011011101010111001101110100011011110110110100100000010001100100011001010100 K
1D
0E
b1 -
b1 1
b111011 .
b111011 2
#11000
0!
0'
0"
b1110110011000010110110001101001011001000010000001000110010001100101010000100000011001100111010101101110011000110111010000110011 K
0J
0D
0I
b1 ,
b1 0
#12000
b101010101101110011010110110111001101111011101110110111000100000011011110111000001100011011011110110010001100101 K
b0 -
b0 1
b0 ,
b0 0
b1111111 .
b1111111 2
