decode_execute/riscv_defines.vh

//opcode macros
//funct3 macros
//funct7 macros
//ALU operation macros
//writeback select macros
//immediate type macros
//FFT custom instruction macros
`ifndef RISCV_DEFINES_VH
`define RISCV_DEFINES_VH

// ============================================================
// Basic architectural parameters
// ============================================================
`define XLEN           32
`define REG_ADDR_W     5
`define INSTR_W        32
`define DATA_W         32
`define IMEM_DEPTH     1024
`define DMEM_DEPTH     1024
`define RESET_PC             0
// ============================================================
// RV32I opcodes
// ============================================================
`define OPCODE_OP      7'b0110011   // R-type
`define OPCODE_OP_IMM  7'b0010011   // I-type ALU
`define OPCODE_LOAD    7'b0000011   // LW
`define OPCODE_STORE   7'b0100011   // SW
`define OPCODE_BRANCH  7'b1100011   // BEQ/BNE
`define OPCODE_JAL     7'b1101111   // JAL

// ============================================================
// Custom opcode space for FFT instruction
// custom-0 opcode
// ============================================================
`define OPCODE_FFT     7'b0001011

// ============================================================
// funct3 values
// ============================================================
`define FUNCT3_ADD_SUB 3'b000
`define FUNCT3_XOR     3'b100
`define FUNCT3_OR      3'b110
`define FUNCT3_AND     3'b111

`define FUNCT3_ADDI    3'b000

`define FUNCT3_LW      3'b010
`define FUNCT3_SW      3'b010

`define FUNCT3_BEQ     3'b000
`define FUNCT3_BNE     3'b001

// ============================================================
// funct7 values
// ============================================================
`define FUNCT7_ADD     7'b0000000
`define FUNCT7_SUB     7'b0100000
`define FUNCT7_LOGIC   7'b0000000

// ============================================================
// FFT custom instruction fields
// Example: FFT_BLY rd, rs1, rs2
// ============================================================
`define FUNCT3_FFT_BLY 3'b000
`define FUNCT7_FFT_BLY 7'b0000001

// ============================================================
// ALU operation select
// ============================================================
`define ALU_ADD        4'd0
`define ALU_SUB        4'd1
`define ALU_AND        4'd2
`define ALU_OR         4'd3
`define ALU_XOR        4'd4
`define ALU_PASS       4'd5

// ============================================================
// Writeback select
// ============================================================
`define WB_ALU         2'd0
`define WB_MEM         2'd1
`define WB_PC4         2'd2
`define WB_FFT         2'd3

// ============================================================
// Immediate type select
// ============================================================
`define IMM_I          3'd0
`define IMM_S          3'd1
`define IMM_B          3'd2
`define IMM_J          3'd3
`define IMM_NONE       3'd4

`endif

decode_execute/decoder.v
`include "riscv_defines.vh"

/*
------------------------------------------------------------------------------
File        : decoder.v
Module      : decoder
Purpose     : Instruction decoder and main control generator for baseline RV32I

Functionality:
- Decodes opcode, funct3, and funct7 from the instruction
- Generates control signals for ALU, immediate generator, memory, writeback,
  branch logic, and FFT custom instruction path

Supported instructions:
- R-type  : ADD, SUB, AND, OR, XOR
- I-type  : ADDI
- LOAD    : LW
- STORE   : SW
- BRANCH  : BEQ, BNE
- JUMP    : JAL
- CUSTOM  : FFT_BLY

Major inputs:
- instr        : 32-bit instruction word

Major outputs:
- rs1_addr     : Source register 1 address
- rs2_addr     : Source register 2 address
- rd_addr      : Destination register address
- reg_write    : Register write enable
- mem_read     : Data memory read enable
- mem_write    : Data memory write enable
- branch       : Branch instruction flag
- jal          : Jump and link flag
- fft_en       : Custom FFT instruction enable
- alu_src      : Selects register/immediate as ALU operand B
- alu_op       : ALU operation control
- wb_sel       : Writeback source select
- imm_sel      : Immediate format select
- branch_ne    : Distinguishes BNE from BEQ
- illegal_instr: Asserted for unsupported instruction

Notes:
- Pure combinational logic
- Only supports current project instruction subset
- Branch decision itself is not made here, only branch type/control decode
------------------------------------------------------------------------------
*/

module decoder (
    input  [31:0] instr,

    output [4:0]  rs1_addr,
    output [4:0]  rs2_addr,
    output [4:0]  rd_addr,

    output reg    reg_write,
    output reg    mem_read,
    output reg    mem_write,
    output reg    branch,
    output reg    branch_ne,
    output reg    jal,
    output reg    fft_en,
    output reg    alu_src,
    output reg [3:0] alu_op,
    output reg [1:0] wb_sel,
    output reg [2:0] imm_sel,
    output reg    illegal_instr
);

    wire [6:0] opcode;
    wire [2:0] funct3;
    wire [6:0] funct7;

    assign opcode   = instr[6:0];
    assign rd_addr  = instr[11:7];
    assign funct3   = instr[14:12];
    assign rs1_addr = instr[19:15];
    assign rs2_addr = instr[24:20];
    assign funct7   = instr[31:25];

    always @(*) begin
        // Default values
        reg_write     = 1'b0;
        mem_read      = 1'b0;
        mem_write     = 1'b0;
        branch        = 1'b0;
        branch_ne     = 1'b0;
        jal           = 1'b0;
        fft_en        = 1'b0;
        alu_src       = 1'b0;
        alu_op        = `ALU_ADD;
        wb_sel        = `WB_ALU;
        imm_sel       = `IMM_NONE;
        illegal_instr = 1'b0;

        case (opcode)

            // --------------------------------------------------
            // R-type: ADD, SUB, AND, OR, XOR
            // --------------------------------------------------
            `OPCODE_OP: begin
                reg_write = 1'b1;
                alu_src   = 1'b0;
                wb_sel    = `WB_ALU;
                imm_sel   = `IMM_NONE;

                case (funct3)
                    `FUNCT3_ADD_SUB: begin
                        if (funct7 == `FUNCT7_ADD)
                            alu_op = `ALU_ADD;
                        else if (funct7 == `FUNCT7_SUB)
                            alu_op = `ALU_SUB;
                        else
                            illegal_instr = 1'b1;
                    end

                    `FUNCT3_AND: begin
                        if (funct7 == `FUNCT7_LOGIC)
                            alu_op = `ALU_AND;
                        else
                            illegal_instr = 1'b1;
                    end

                    `FUNCT3_OR: begin
                        if (funct7 == `FUNCT7_LOGIC)
                            alu_op = `ALU_OR;
                        else
                            illegal_instr = 1'b1;
                    end

                    `FUNCT3_XOR: begin
                        if (funct7 == `FUNCT7_LOGIC)
                            alu_op = `ALU_XOR;
                        else
                            illegal_instr = 1'b1;
                    end

                    default: begin
                        illegal_instr = 1'b1;
                    end
                endcase
            end

            // --------------------------------------------------
            // I-type: ADDI
            // --------------------------------------------------
            `OPCODE_OP_IMM: begin
                reg_write = 1'b1;
                alu_src   = 1'b1;
                wb_sel    = `WB_ALU;
                imm_sel   = `IMM_I;

                case (funct3)
                    `FUNCT3_ADDI: alu_op = `ALU_ADD;
                    default:      illegal_instr = 1'b1;
                endcase
            end

            // --------------------------------------------------
            // LOAD: LW
            // --------------------------------------------------
            `OPCODE_LOAD: begin
                reg_write = 1'b1;
                mem_read  = 1'b1;
                alu_src   = 1'b1;
                wb_sel    = `WB_MEM;
                imm_sel   = `IMM_I;
                alu_op    = `ALU_ADD;

                if (funct3 != `FUNCT3_LW)
                    illegal_instr = 1'b1;
            end

            // --------------------------------------------------
            // STORE: SW
            // --------------------------------------------------
            `OPCODE_STORE: begin
                mem_write = 1'b1;
                alu_src   = 1'b1;
                imm_sel   = `IMM_S;
                alu_op    = `ALU_ADD;

                if (funct3 != `FUNCT3_SW)
                    illegal_instr = 1'b1;
            end

            // --------------------------------------------------
            // BRANCH: BEQ, BNE
            // --------------------------------------------------
            `OPCODE_BRANCH: begin
                branch  = 1'b1;
                alu_src = 1'b0;
                imm_sel = `IMM_B;
                alu_op  = `ALU_SUB;

                case (funct3)
                    `FUNCT3_BEQ: branch_ne = 1'b0;
                    `FUNCT3_BNE: branch_ne = 1'b1;
                    default:     illegal_instr = 1'b1;
                endcase
            end

            // --------------------------------------------------
            // JAL
            // --------------------------------------------------
            `OPCODE_JAL: begin
                reg_write = 1'b1;
                jal       = 1'b1;
                wb_sel    = `WB_PC4;
                imm_sel   = `IMM_J;
            end

            // --------------------------------------------------
            // Custom FFT instruction
            // --------------------------------------------------
            `OPCODE_FFT: begin
                reg_write = 1'b1;
                fft_en    = 1'b1;
                wb_sel    = `WB_FFT;
                alu_src   = 1'b0;
                imm_sel   = `IMM_NONE;

                if ((funct3 == `FUNCT3_FFT_BLY) && (funct7 == `FUNCT7_FFT_BLY))
                    alu_op = `ALU_PASS;
                else
                    illegal_instr = 1'b1;
            end

            // --------------------------------------------------
            // Unsupported instruction
            // --------------------------------------------------
            default: begin
                illegal_instr = 1'b1;
            end
        endcase
    end

endmodule

decode_execute/tb_decoder.v
`timescale 1ns/1ps
`include "riscv_defines.vh"

/*
------------------------------------------------------------------------------
File        : tb_decoder.v
Testbench   : tb_decoder
Purpose     : Self-checking testbench for decoder.v

What this TB verifies:
1. R-type decode for ADD, SUB, AND, OR, XOR
2. I-type decode for ADDI
3. Load decode for LW
4. Store decode for SW
5. Branch decode for BEQ and BNE
6. Jump decode for JAL
7. Custom decode for FFT_BLY
8. Illegal instruction detection

DUT inputs driven by TB:
- instr          : 32-bit instruction word

DUT outputs checked by TB:
- rs1_addr       : Source register 1 address
- rs2_addr       : Source register 2 address
- rd_addr        : Destination register address
- reg_write      : Register write enable
- mem_read       : Memory read enable
- mem_write      : Memory write enable
- branch         : Branch flag
- branch_ne      : BNE flag
- jal            : JAL flag
- fft_en         : FFT instruction enable
- alu_src        : ALU source select
- alu_op         : ALU operation control
- wb_sel         : Writeback source select
- imm_sel        : Immediate format select
- illegal_instr  : Unsupported instruction flag

Pass/Fail method:
- TB applies known instruction encodings
- TB checks important output controls and register fields
- Prints PASS/FAIL messages using $display
- Dumps waveform file for GTKWave debug

Run command (Icarus Verilog):
- Compile : iverilog -o decoder_tb decoder.v tb_decoder.v
- Run     : vvp decoder_tb
- Waveform: gtkwave tb_decoder.vcd

Notes:
- Pure Verilog testbench, no SystemVerilog features used
- Uses only current project instruction subset
------------------------------------------------------------------------------
*/

module tb_decoder;

    reg  [31:0] instr;

    wire [4:0] rs1_addr;
    wire [4:0] rs2_addr;
    wire [4:0] rd_addr;

    wire       reg_write;
    wire       mem_read;
    wire       mem_write;
    wire       branch;
    wire       branch_ne;
    wire       jal;
    wire       fft_en;
    wire       alu_src;
    wire [3:0] alu_op;
    wire [1:0] wb_sel;
    wire [2:0] imm_sel;
    wire       illegal_instr;

    integer errors;

    decoder uut (
        .instr         (instr),
        .rs1_addr      (rs1_addr),
        .rs2_addr      (rs2_addr),
        .rd_addr       (rd_addr),
        .reg_write     (reg_write),
        .mem_read      (mem_read),
        .mem_write     (mem_write),
        .branch        (branch),
        .branch_ne     (branch_ne),
        .jal           (jal),
        .fft_en        (fft_en),
        .alu_src       (alu_src),
        .alu_op        (alu_op),
        .wb_sel        (wb_sel),
        .imm_sel       (imm_sel),
        .illegal_instr (illegal_instr)
    );

    task check_decode;
        input [4:0] exp_rs1;
        input [4:0] exp_rs2;
        input [4:0] exp_rd;
        input       exp_reg_write;
        input       exp_mem_read;
        input       exp_mem_write;
        input       exp_branch;
        input       exp_branch_ne;
        input       exp_jal;
        input       exp_fft_en;
        input       exp_alu_src;
        input [3:0] exp_alu_op;
        input [1:0] exp_wb_sel;
        input [2:0] exp_imm_sel;
        input       exp_illegal;
        input [127:0] test_name;
        begin
            #1;
            if ((rs1_addr      !== exp_rs1)      ||
                (rs2_addr      !== exp_rs2)      ||
                (rd_addr       !== exp_rd)       ||
                (reg_write     !== exp_reg_write)||
                (mem_read      !== exp_mem_read) ||
                (mem_write     !== exp_mem_write)||
                (branch        !== exp_branch)   ||
                (branch_ne     !== exp_branch_ne)||
                (jal           !== exp_jal)      ||
                (fft_en        !== exp_fft_en)   ||
                (alu_src       !== exp_alu_src)  ||
                (alu_op        !== exp_alu_op)   ||
                (wb_sel        !== exp_wb_sel)   ||
                (imm_sel       !== exp_imm_sel)  ||
                (illegal_instr !== exp_illegal)) begin

                $display("FAIL : %s", test_name);
                $display("       instr=%h", instr);
                $display("       rs1=%0d rs2=%0d rd=%0d", rs1_addr, rs2_addr, rd_addr);
                $display("       reg_write=%b mem_read=%b mem_write=%b", reg_write, mem_read, mem_write);
                $display("       branch=%b branch_ne=%b jal=%b fft_en=%b", branch, branch_ne, jal, fft_en);
                $display("       alu_src=%b alu_op=%h wb_sel=%h imm_sel=%h illegal=%b",
                          alu_src, alu_op, wb_sel, imm_sel, illegal_instr);
                errors = errors + 1;
            end
            else begin
                $display("PASS : %s", test_name);
            end
        end
    endtask

    initial begin
        $dumpfile("tb_decoder.vcd");
        $dumpvars(0, tb_decoder);

        errors = 0;

        // ------------------------------------------------------
        // ADD  x5, x1, x2
        // funct7 rs2  rs1  funct3 rd   opcode
        // 0000000 00010 00001 000 00101 0110011
        // ------------------------------------------------------
        instr = 32'b0000000_00010_00001_000_00101_0110011;
        check_decode(5'd1, 5'd2, 5'd5,
                     1'b1, 1'b0, 1'b0, 1'b0, 1'b0, 1'b0, 1'b0,
                     1'b0, `ALU_ADD, `WB_ALU, `IMM_NONE, 1'b0,
                     "ADD_DECODE");

        // SUB x6, x3, x4
        instr = 32'b0100000_00100_00011_000_00110_0110011;
        check_decode(5'd3, 5'd4, 5'd6,
                     1'b1, 1'b0, 1'b0, 1'b0, 1'b0, 1'b0, 1'b0,
                     1'b0, `ALU_SUB, `WB_ALU, `IMM_NONE, 1'b0,
                     "SUB_DECODE");

        // AND x7, x8, x9
        instr = 32'b0000000_01001_01000_111_00111_0110011;
        check_decode(5'd8, 5'd9, 5'd7,
                     1'b1, 1'b0, 1'b0, 1'b0, 1'b0, 1'b0, 1'b0,
                     1'b0, `ALU_AND, `WB_ALU, `IMM_NONE, 1'b0,
                     "AND_DECODE");

        // OR x10, x11, x12
        instr = 32'b0000000_01100_01011_110_01010_0110011;
        check_decode(5'd11, 5'd12, 5'd10,
                     1'b1, 1'b0, 1'b0, 1'b0, 1'b0, 1'b0, 1'b0,
                     1'b0, `ALU_OR, `WB_ALU, `IMM_NONE, 1'b0,
                     "OR_DECODE");

        // XOR x13, x14, x15
        instr = 32'b0000000_01111_01110_100_01101_0110011;
        check_decode(5'd14, 5'd15, 5'd13,
                     1'b1, 1'b0, 1'b0, 1'b0, 1'b0, 1'b0, 1'b0,
                     1'b0, `ALU_XOR, `WB_ALU, `IMM_NONE, 1'b0,
                     "XOR_DECODE");

        // ADDI x5, x1, 10
        instr = 32'b000000001010_00001_000_00101_0010011;
        check_decode(5'd1, 5'd10, 5'd5,
                     1'b1, 1'b0, 1'b0, 1'b0, 1'b0, 1'b0, 1'b0,
                     1'b1, `ALU_ADD, `WB_ALU, `IMM_I, 1'b0,
                     "ADDI_DECODE");

        // LW x4, 8(x2)
        instr = 32'b000000001000_00010_010_00100_0000011;
        check_decode(5'd2, 5'd8, 5'd4,
                     1'b1, 1'b1, 1'b0, 1'b0, 1'b0, 1'b0, 1'b0,
                     1'b1, `ALU_ADD, `WB_MEM, `IMM_I, 1'b0,
                     "LW_DECODE");

        // SW x4, 12(x2)
        instr = 32'b0000000_00100_00010_010_01100_0100011;
        check_decode(5'd2, 5'd4, 5'd12,
                     1'b0, 1'b0, 1'b1, 1'b0, 1'b0, 1'b0, 1'b0,
                     1'b1, `ALU_ADD, `WB_ALU, `IMM_S, 1'b0,
                     "SW_DECODE");

        // BEQ x1, x2, offset
        instr = 32'b0000000_00010_00001_000_00000_1100011;
        check_decode(5'd1, 5'd2, 5'd0,
                     1'b0, 1'b0, 1'b0, 1'b1, 1'b0, 1'b0, 1'b0,
                     1'b0, `ALU_SUB, `WB_ALU, `IMM_B, 1'b0,
                     "BEQ_DECODE");

        // BNE x3, x4, offset
        instr = 32'b0000000_00100_00011_001_00000_1100011;
        check_decode(5'd3, 5'd4, 5'd0,
                     1'b0, 1'b0, 1'b0, 1'b1, 1'b1, 1'b0, 1'b0,
                     1'b0, `ALU_SUB, `WB_ALU, `IMM_B, 1'b0,
                     "BNE_DECODE");

        // JAL x1, offset
        instr = 32'b00000000000000000000_00001_1101111;
        check_decode(5'd0, 5'd0, 5'd1,
                     1'b1, 1'b0, 1'b0, 1'b0, 1'b0, 1'b1, 1'b0,
                     1'b0, `ALU_ADD, `WB_PC4, `IMM_J, 1'b0,
                     "JAL_DECODE");

        // FFT_BLY x5, x1, x2
        instr = 32'b0000001_00010_00001_000_00101_0001011;
        check_decode(5'd1, 5'd2, 5'd5,
                     1'b1, 1'b0, 1'b0, 1'b0, 1'b0, 1'b0, 1'b1,
                     1'b0, `ALU_PASS, `WB_FFT, `IMM_NONE, 1'b0,
                     "FFT_DECODE");

        // Illegal instruction: unsupported R-type funct3
        instr = 32'b0000000_00010_00001_001_00101_0110011;
        check_decode(5'd1, 5'd2, 5'd5,
                     1'b1, 1'b0, 1'b0, 1'b0, 1'b0, 1'b0, 1'b0,
                     1'b0, `ALU_ADD, `WB_ALU, `IMM_NONE, 1'b1,
                     "ILLEGAL_RTYPE");

        if (errors == 0)
            $display("\nALL DECODER TESTS PASSED\n");
        else
            $display("\nDECODER TESTS FAILED : total errors = %0d\n", errors);

        $finish;
    end

endmodule

decode_execute/tb_decoder.vcd
$date
	Tue Apr 14 20:50:31 2026
$end
$version
	Icarus Verilog
$end
$timescale
	1ps
$end
$scope module tb_decoder $end
$var wire 2 ! wb_sel [1:0] $end
$var wire 5 " rs2_addr [4:0] $end
$var wire 5 # rs1_addr [4:0] $end
$var wire 1 $ reg_write $end
$var wire 5 % rd_addr [4:0] $end
$var wire 1 & mem_write $end
$var wire 1 ' mem_read $end
$var wire 1 ( jal $end
$var wire 3 ) imm_sel [2:0] $end
$var wire 1 * illegal_instr $end
$var wire 1 + fft_en $end
$var wire 1 , branch_ne $end
$var wire 1 - branch $end
$var wire 1 . alu_src $end
$var wire 4 / alu_op [3:0] $end
$var reg 32 0 instr [31:0] $end
$var integer 32 1 errors [31:0] $end
$scope module uut $end
$var wire 32 2 instr [31:0] $end
$var wire 5 3 rs2_addr [4:0] $end
$var wire 5 4 rs1_addr [4:0] $end
$var wire 5 5 rd_addr [4:0] $end
$var wire 7 6 opcode [6:0] $end
$var wire 7 7 funct7 [6:0] $end
$var wire 3 8 funct3 [2:0] $end
$var reg 4 9 alu_op [3:0] $end
$var reg 1 . alu_src $end
$var reg 1 - branch $end
$var reg 1 , branch_ne $end
$var reg 1 + fft_en $end
$var reg 1 * illegal_instr $end
$var reg 3 : imm_sel [2:0] $end
$var reg 1 ( jal $end
$var reg 1 ' mem_read $end
$var reg 1 & mem_write $end
$var reg 1 $ reg_write $end
$var reg 2 ; wb_sel [1:0] $end
$upscope $end
$scope task check_decode $end
$var reg 4 < exp_alu_op [3:0] $end
$var reg 1 = exp_alu_src $end
$var reg 1 > exp_branch $end
$var reg 1 ? exp_branch_ne $end
$var reg 1 @ exp_fft_en $end
$var reg 1 A exp_illegal $end
$var reg 3 B exp_imm_sel [2:0] $end
$var reg 1 C exp_jal $end
$var reg 1 D exp_mem_read $end
$var reg 1 E exp_mem_write $end
$var reg 5 F exp_rd [4:0] $end
$var reg 1 G exp_reg_write $end
$var reg 5 H exp_rs1 [4:0] $end
$var reg 5 I exp_rs2 [4:0] $end
$var reg 2 J exp_wb_sel [1:0] $end
$var reg 128 K test_name [127:0] $end
$upscope $end
$upscope $end
$enddefinitions $end
$comment Show the parameter values. $end
$dumpall
$end
#0
$dumpvars
b1000001010001000100010001011111010001000100010101000011010011110100010001000101 K
b0 J
b10 I
b1 H
1G
b101 F
0E
0D
0C
b100 B
0A
0@
0?
0>
0=
b0 <
b0 ;
b100 :
b0 9
b0 8
b0 7
b110011 6
b101 5
b1 4
b10 3
b1000001000001010110011 2
b0 1
b1000001000001010110011 0
b0 /
0.
0-
0,
0+
0*
b100 )
0(
0'
0&
b101 %
1$
b1 #
b10 "
b0 !
$end
#1000
b1 /
b1 9
1$
b110 %
b110 5
b11 #
b11 4
b100 "
b100 3
b100000 7
b1010011010101010100001001011111010001000100010101000011010011110100010001000101 K
b1 <
b110 F
b100 I
b11 H
b1000000010000011000001100110011 0
b1000000010000011000001100110011 2
#2000
b10 /
b10 9
1$
b111 %
b111 5
b111 8
b1000 #
b1000 4
b1001 "
b1001 3
b0 7
b1000001010011100100010001011111010001000100010101000011010011110100010001000101 K
b10 <
b111 F
b1001 I
b1000 H
b100101000111001110110011 0
b100101000111001110110011 2
#3000
b11 /
b11 9
1$
b1010 %
b1010 5
b110 8
b1011 #
b1011 4
b1100 "
b1100 3
b10011110101001001011111010001000100010101000011010011110100010001000101 K
b11 <
b1010 F
b1100 I
b1011 H
b110001011110010100110011 0
b110001011110010100110011 2
#4000
b100 /
b100 9
1$
b1101 %
b1101 5
b100 8
b1110 #
b1110 4
b1111 "
b1111 3
b1011000010011110101001001011111010001000100010101000011010011110100010001000101 K
b100 <
b1101 F
b1111 I
b1110 H
b111101110100011010110011 0
b111101110100011010110011 2
#5000
b0 )
b0 :
1.
b0 /
b0 9
1$
b10011 6
b101 %
b101 5
b0 8
b1 #
b1 4
b1010 "
b1010 3
b100000101000100010001000100100101011111010001000100010101000011010011110100010001000101 K
b0 B
b0 <
1=
b101 F
b1010 I
b1 H
b101000001000001010010011 0
b101000001000001010010011 2
#6000
b1 !
b1 ;
1'
b0 )
b0 :
1.
1$
b11 6
b100 %
b100 5
b10 8
b10 #
b10 4
b1000 "
b1000 3
b10011000101011101011111010001000100010101000011010011110100010001000101 K
b1 J
1D
b100 F
b1000 I
b10 H
b100000010010001000000011 0
b100000010010001000000011 2
#7000
1&
b1 )
b1 :
b0 !
b0 ;
1.
0'
0$
b100011 6
b1100 %
b1100 5
b100 "
b100 3
b10100110101011101011111010001000100010101000011010011110100010001000101 K
b1 B
b0 J
1E
0D
0G
b1100 F
b100 I
b10000010010011000100011 0
b10000010010011000100011 2
#8000
b1 /
b1 9
1-
b10 )
b10 :
0.
0&
b1100011 6
b0 %
b0 5
b0 8
b1 #
b1 4
b10 "
b10 3
b1000010010001010101000101011111010001000100010101000011010011110100010001000101 K
b10 B
b1 <
0=
1>
0E
b0 F
b10 I
b1 H
b1000001000000001100011 0
b1000001000000001100011 2
#9000
1,
b10 )
b10 :
b1 /
b1 9
1-
b1 8
b11 #
b11 4
b100 "
b100 3
b1000010010011100100010101011111010001000100010101000011010011110100010001000101 K
1?
b100 I
b11 H
b10000011001000001100011 0
b10000011001000001100011 2
#10000
b10 !
b10 ;
1(
1$
b11 )
b11 :
b0 /
b0 9
0,
0-
b1101111 6
b1 %
b1 5
b0 8
b0 #
b0 4
b0 "
b0 3
b1001010010000010100110001011111010001000100010101000011010011110100010001000101 K
b11 B
b10 J
b0 <
1C
0?
0>
1G
b1 F
b0 I
b0 H
b11101111 0
b11101111 2
#11000
b101 /
b101 9
1+
b100 )
b100 :
b11 !
b11 ;
0(
1$
b1011 6
b101 %
b101 5
b1 #
b1 4
b10 "
b10 3
b1 7
b1000110010001100101010001011111010001000100010101000011010011110100010001000101 K
b100 B
b11 J
b101 <
1@
0C
b101 F
b10 I
b1 H
b10001000001000001010001011 0
b10001000001000001010001011 2
#12000
1*
b0 !
b0 ;
b0 /
b0 9
0+
1$
b110011 6
b1 8
b0 7
b1001001010011000100110001000101010001110100000101001100010111110101001001010100010110010101000001000101 K
1A
b0 J
b0 <
0@
b1000001001001010110011 0
b1000001001001010110011 2
