decode_execute/riscv_defines.vh

//opcode macros
//funct3 macros
//funct7 macros
//ALU operation macros
//writeback select macros
//immediate type macros
//FFT custom instruction macros
`ifndef RISCV_DEFINES_VH
`define RISCV_DEFINES_VH

// ============================================================
// Basic architectural parameters
// ============================================================
`define XLEN           32
`define REG_ADDR_W     5
`define INSTR_W        32
`define DATA_W         32
`define IMEM_DEPTH     1024
`define DMEM_DEPTH     1024
`define RESET_PC             0
// ============================================================
// RV32I opcodes
// ============================================================
`define OPCODE_OP      7'b0110011   // R-type
`define OPCODE_OP_IMM  7'b0010011   // I-type ALU
`define OPCODE_LOAD    7'b0000011   // LW
`define OPCODE_STORE   7'b0100011   // SW
`define OPCODE_BRANCH  7'b1100011   // BEQ/BNE
`define OPCODE_JAL     7'b1101111   // JAL

// ============================================================
// Custom opcode space for FFT instruction
// custom-0 opcode
// ============================================================
`define OPCODE_FFT     7'b0001011

// ============================================================
// funct3 values
// ============================================================
`define FUNCT3_ADD_SUB 3'b000
`define FUNCT3_XOR     3'b100
`define FUNCT3_OR      3'b110
`define FUNCT3_AND     3'b111

`define FUNCT3_ADDI    3'b000

`define FUNCT3_LW      3'b010
`define FUNCT3_SW      3'b010

`define FUNCT3_BEQ     3'b000
`define FUNCT3_BNE     3'b001

// ============================================================
// funct7 values
// ============================================================
`define FUNCT7_ADD     7'b0000000
`define FUNCT7_SUB     7'b0100000
`define FUNCT7_LOGIC   7'b0000000

// ============================================================
// FFT custom instruction fields
// Example: FFT_BLY rd, rs1, rs2
// ============================================================
`define FUNCT3_FFT_BLY 3'b000
`define FUNCT7_FFT_BLY 7'b0000001

// ============================================================
// ALU operation select
// ============================================================
`define ALU_ADD        4'd0
`define ALU_SUB        4'd1
`define ALU_AND        4'd2
`define ALU_OR         4'd3
`define ALU_XOR        4'd4
`define ALU_PASS       4'd5

// ============================================================
// Writeback select
// ============================================================
`define WB_ALU         2'd0
`define WB_MEM         2'd1
`define WB_PC4         2'd2
`define WB_FFT         2'd3

// ============================================================
// Immediate type select
// ============================================================
`define IMM_I          3'd0
`define IMM_S          3'd1
`define IMM_B          3'd2
`define IMM_J          3'd3
`define IMM_NONE       3'd4

`endif

data_mem.v
`include "riscv_defines.vh"

/*
------------------------------------------------------------------------------
File        : data_mem.v
Module      : data_mem
Purpose     : Data memory for baseline RV32I load/store stage

Functionality:
- Stores 32-bit data words
- Supports SW write and LW read for current project subset
- Uses word-aligned addressing with addr_in[31:2]

Major inputs:
- clk         : Clock input
- mem_read    : Read enable
- mem_write   : Write enable
- addr_in     : Byte address from ALU
- write_data  : Data to be written into memory

Major outputs:
- read_data   : Data read from memory

Parameters:
- MEM_DEPTH   : Number of 32-bit words in data memory

Notes:
- Synchronous write
- Combinational read
- Word-aligned access uses addr_in[31:2]
- Lower 2 bits of address are ignored for current LW/SW-only design
- Out-of-range read returns 0
- Out-of-range write is ignored
- No reset is used because memory arrays are typically not cleared by reset in
  synthesizable RTL unless specifically required
- Written in Verilog-only style for Icarus compatibility
------------------------------------------------------------------------------
*/

module data_mem #(
    parameter MEM_DEPTH = 256
)(
    input                  clk,
    input                  mem_read,
    input                  mem_write,
    input  [`XLEN-1:0]     addr_in,
    input  [`XLEN-1:0]     write_data,
    output reg [`XLEN-1:0] read_data
);

    reg [`XLEN-1:0] mem [0:MEM_DEPTH-1];

    wire [`XLEN-1:0] word_addr;
    assign word_addr = addr_in >> 2;

    // Synchronous write
    always @(posedge clk) begin
        if (mem_write && (word_addr < MEM_DEPTH))
            mem[word_addr] <= write_data;
    end

    // Combinational read
    always @(*) begin
        if (mem_read && (word_addr < MEM_DEPTH))
            read_data = mem[word_addr];
        else
            read_data = {`XLEN{1'b0}};
    end

endmodule

tb_data_mem.v
`timescale 1ns/1ps
`include "riscv_defines.vh"

/*
------------------------------------------------------------------------------
File        : tb_data_mem.v
Testbench   : tb_data_mem
Purpose     : Self-checking testbench for data_mem.v

What this TB verifies:
1. Write occurs only on positive clock edge
2. Read returns previously written data
3. No write occurs when mem_write = 0
4. Read output is zero when mem_read = 0
5. Word-aligned addressing uses addr_in[31:2]
6. Different addresses store independent values
7. Out-of-range read returns zero

DUT inputs driven by TB:
- clk         : Clock input
- mem_read    : Read enable
- mem_write   : Write enable
- addr_in     : Byte address from ALU
- write_data  : Data written into memory

DUT outputs checked by TB:
- read_data   : Data read from memory

Pass/Fail method:
- TB performs directed write/read sequences
- TB checks read_data against expected values
- Prints PASS/FAIL messages using $display
- Dumps waveform file for GTKWave debug

Run command (Icarus Verilog):
- Compile : iverilog -o dmem_tb data_mem.v tb_data_mem.v
- Run     : vvp dmem_tb
- Waveform: gtkwave tb_data_mem.vcd

Notes:
- Pure Verilog testbench, no SystemVerilog features used
- This TB assumes synchronous write and combinational read behavior
------------------------------------------------------------------------------
*/

module tb_data_mem;

    reg              clk;
    reg              mem_read;
    reg              mem_write;
    reg  [`XLEN-1:0] addr_in;
    reg  [`XLEN-1:0] write_data;

    wire [`XLEN-1:0] read_data;

    integer errors;

    data_mem #(
        .MEM_DEPTH(16)
    ) uut (
        .clk        (clk),
        .mem_read   (mem_read),
        .mem_write  (mem_write),
        .addr_in    (addr_in),
        .write_data (write_data),
        .read_data  (read_data)
    );

    // Clock generation
    initial begin
        clk = 1'b0;
        forever #5 clk = ~clk;
    end

    task check_read;
        input [`XLEN-1:0] expected_data;
        input [127:0]     test_name;
        begin
            #1;
            if (read_data !== expected_data) begin
                $display("FAIL : %s", test_name);
                $display("       addr_in=%h mem_read=%b mem_write=%b write_data=%h",
                         addr_in, mem_read, mem_write, write_data);
                $display("       expected read_data=%h", expected_data);
                $display("       got      read_data=%h", read_data);
                errors = errors + 1;
            end
            else begin
                $display("PASS : %s  read_data=%h", test_name, read_data);
            end
        end
    endtask

    task write_word;
        input [`XLEN-1:0] addr;
        input [`XLEN-1:0] data;
        begin
            @(negedge clk);
            addr_in    = addr;
            write_data = data;
            mem_write  = 1'b1;
            mem_read   = 1'b0;
            @(posedge clk);
            #1;
            mem_write  = 1'b0;
        end
    endtask

    initial begin
        $dumpfile("tb_data_mem.vcd");
        $dumpvars(0, tb_data_mem);

        errors = 0;

        // Initialize
        mem_read   = 1'b0;
        mem_write  = 1'b0;
        addr_in    = 32'h0000_0000;
        write_data = 32'h0000_0000;

        // ------------------------------------------------------
        // Test 1: Read disabled => output should be zero
        // ------------------------------------------------------
        addr_in   = 32'h0000_0000;
        mem_read  = 1'b0;
        mem_write = 1'b0;
        check_read(32'h0000_0000, "READ_DISABLED_ZERO");

        // ------------------------------------------------------
        // Test 2: Write one word at address 0
        // ------------------------------------------------------
        write_word(32'h0000_0000, 32'hDEAD_BEEF);
        mem_read = 1'b1;
        addr_in   = 32'h0000_0000;
        check_read(32'hDEAD_BEEF, "WRITE_READ_ADDR0");

        // ------------------------------------------------------
        // Test 3: Write another word at address 4
        // ------------------------------------------------------
        write_word(32'h0000_0004, 32'h1234_5678);
        mem_read = 1'b1;
        addr_in   = 32'h0000_0004;
        check_read(32'h1234_5678, "WRITE_READ_ADDR1");

        // ------------------------------------------------------
        // Test 4: Original address still holds old value
        // ------------------------------------------------------
        addr_in  = 32'h0000_0000;
        mem_read = 1'b1;
        check_read(32'hDEAD_BEEF, "ADDR0_UNCHANGED");

        // ------------------------------------------------------
        // Test 5: Word alignment check
        // addr 0x00000006 maps to word address 1
        // ------------------------------------------------------
        addr_in  = 32'h0000_0006;
        mem_read = 1'b1;
        check_read(32'h1234_5678, "WORD_ALIGN_ADDR1");

        // ------------------------------------------------------
        // Test 6: No write when mem_write = 0
        // ------------------------------------------------------
        @(negedge clk);
        addr_in    = 32'h0000_0008;
        write_data = 32'hAAAA_AAAA;
        mem_write  = 1'b0;
        mem_read   = 1'b1;
        @(posedge clk);
        #1;
        check_read(32'hxxxx_xxxx, "NO_WRITE_UNKNOWN_OR_UNINITIALIZED");

        // ------------------------------------------------------
        // Test 7: Read disabled again => zero output
        // ------------------------------------------------------
        mem_read = 1'b0;
        addr_in  = 32'h0000_0000;
        check_read(32'h0000_0000, "READ_DISABLED_AGAIN");

        // ------------------------------------------------------
        // Test 8: Out-of-range read => zero output
        // MEM_DEPTH = 16, valid word addresses are 0 to 15
        // address 0x00000100 => word address 64 => out of range
        // ------------------------------------------------------
        addr_in  = 32'h0000_0100;
        mem_read = 1'b1;
        check_read(32'h0000_0000, "OUT_OF_RANGE_READ");

        if (errors == 0)
            $display("\nALL DATA_MEM TESTS PASSED\n");
        else
            $display("\nDATA_MEM TESTS FAILED : total errors = %0d\n", errors);

        $finish;
    end

endmodule

tb_data_mem.vcd
$date
	Sat May 02 22:02:06 2026
$end
$version
	Icarus Verilog
$end
$timescale
	1ps
$end
$scope module tb_data_mem $end
$var wire 32 ! read_data [31:0] $end
$var reg 32 " addr_in [31:0] $end
$var reg 1 # clk $end
$var reg 1 $ mem_read $end
$var reg 1 % mem_write $end
$var reg 32 & write_data [31:0] $end
$var integer 32 ' errors [31:0] $end
$scope module uut $end
$var wire 32 ( addr_in [31:0] $end
$var wire 1 # clk $end
$var wire 1 $ mem_read $end
$var wire 1 % mem_write $end
$var wire 32 ) write_data [31:0] $end
$var wire 32 * word_addr [31:0] $end
$var parameter 32 + MEM_DEPTH $end
$var reg 32 , read_data [31:0] $end
$upscope $end
$scope task check_read $end
$var reg 32 - expected_data [31:0] $end
$var reg 128 . test_name [127:0] $end
$upscope $end
$scope task write_word $end
$var reg 32 / addr [31:0] $end
$var reg 32 0 data [31:0] $end
$upscope $end
$upscope $end
$enddefinitions $end
$comment Show the parameter values. $end
$dumpall
b10000 +
$end
#0
$dumpvars
bx 0
bx /
b1000001010001000101111101000100010010010101001101000001010000100100110001000101010001000101111101011010010001010101001001001111 .
b0 -
b0 ,
b0 *
b0 )
b0 (
b0 '
b0 &
0%
0$
0#
b0 "
b0 !
$end
#1000
b11011110101011011011111011101111 0
b0 /
#5000
1#
#10000
1%
b11011110101011011011111011101111 &
b11011110101011011011111011101111 )
0#
#15000
1#
#16000
b11011110101011011011111011101111 !
b11011110101011011011111011101111 ,
b1010111010100100100100101010100010001010101111101010010010001010100000101000100010111110100000101000100010001000101001000110000 .
b11011110101011011011111011101111 -
1$
0%
#17000
b10010001101000101011001111000 0
b100 /
#20000
b0 !
b0 ,
b1 *
0$
1%
b10010001101000101011001111000 &
b10010001101000101011001111000 )
b100 "
b100 (
0#
#25000
1#
#26000
b10010001101000101011001111000 !
b10010001101000101011001111000 ,
b1010111010100100100100101010100010001010101111101010010010001010100000101000100010111110100000101000100010001000101001000110001 .
b10010001101000101011001111000 -
1$
0%
#27000
b11011110101011011011111011101111 !
b11011110101011011011111011101111 ,
b0 *
b10000010100010001000100010100100011000001011111010101010100111001000011010010000100000101001110010001110100010101000100 .
b11011110101011011011111011101111 -
b0 "
b0 (
#28000
b10010001101000101011001111000 !
b10010001101000101011001111000 ,
b1 *
b1010111010011110101001001000100010111110100000101001100010010010100011101001110010111110100000101000100010001000101001000110001 .
b10010001101000101011001111000 -
b110 "
b110 (
#30000
bx !
bx ,
b10 *
b10101010101010101010101010101010 &
b10101010101010101010101010101010 )
b1000 "
b1000 (
0#
#35000
1#
#36000
b1001111010100100101111101010101010011100100100101001110010010010101010001001001010000010100110001001001010110100100010101000100 .
bx -
#37000
b0 *
b0 !
b0 ,
b1000100010111110100010001001001010100110100000101000010010011000100010101000100010111110100000101000111010000010100100101001110 .
b0 -
b0 "
b0 (
0$
#38000
b1000000 *
b1010101010101000101111101001111010001100101111101010010010000010100111001000111010001010101111101010010010001010100000101000100 .
1$
b100000000 "
b100000000 (
