mem_wb_stage/wb_mux.v
`timescale 1ns/1ps

module wb_mux (
    input  wire [31:0] mem_data,
    input  wire [31:0] alu_data,
    input  wire [31:0] pc_plus4,
    input  wire        mem_to_reg,
    input  wire        jump,
    output reg  [31:0] wb_data
);

    always @(*) begin
        if (jump)
            wb_data = pc_plus4;     // JAL writes PC+4 to rd
        else if (mem_to_reg)
            wb_data = mem_data;     // LW writes loaded data
        else
            wb_data = alu_data;     // ALU / FFT result
    end

endmodule

mem_wb_stage/mem_wb_reg.v
`timescale 1ns/1ps

module mem_wb_reg (
    input  wire        clk,
    input  wire        rst_n,

    input  wire [31:0] mem_read_data_in,
    input  wire [31:0] alu_result_in,
    input  wire [31:0] pc_plus4_in,
    input  wire [4:0]  rd_addr_in,

    input  wire        reg_write_in,
    input  wire        mem_to_reg_in,
    input  wire        jump_in,

    output reg  [31:0] mem_read_data_out,
    output reg  [31:0] alu_result_out,
    output reg  [31:0] pc_plus4_out,
    output reg  [4:0]  rd_addr_out,

    output reg         reg_write_out,
    output reg         mem_to_reg_out,
    output reg         jump_out
);

    always @(posedge clk or negedge rst_n) begin
        if (!rst_n) begin
            mem_read_data_out <= 32'b0;
            alu_result_out    <= 32'b0;
            pc_plus4_out      <= 32'b0;
            rd_addr_out       <= 5'b0;
            reg_write_out     <= 1'b0;
            mem_to_reg_out    <= 1'b0;
            jump_out          <= 1'b0;
        end
        else begin
            mem_read_data_out <= mem_read_data_in;
            alu_result_out    <= alu_result_in;
            pc_plus4_out      <= pc_plus4_in;
            rd_addr_out       <= rd_addr_in;
            reg_write_out     <= reg_write_in;
            mem_to_reg_out    <= mem_to_reg_in;
            jump_out          <= jump_in;
        end
    end

endmodule

mem_wb_stage/mem_wb.v
`timescale 1ns/1ps

module mem_wb (
    input  wire        clk,
    input  wire        rst_n,

    // Inputs from MEM stage
    input  wire [31:0] mem_read_data_in,
    input  wire [31:0] alu_result_in,
    input  wire [31:0] pc_plus4_in,
    input  wire [4:0]  rd_addr_in,

    input  wire        reg_write_in,
    input  wire        mem_to_reg_in,
    input  wire        jump_in,

    // Outputs to register file
    output wire [31:0] wb_data_out,
    output wire [4:0]  wb_rd_addr_out,
    output wire        wb_reg_write_out
);

    wire [31:0] mem_read_data_w;
    wire [31:0] alu_result_w;
    wire [31:0] pc_plus4_w;
    wire [4:0]  rd_addr_w;

    wire        reg_write_w;
    wire        mem_to_reg_w;
    wire        jump_w;

    mem_wb_reg u_mem_wb_reg (
        .clk              (clk),
        .rst_n            (rst_n),
        .mem_read_data_in (mem_read_data_in),
        .alu_result_in    (alu_result_in),
        .pc_plus4_in      (pc_plus4_in),
        .rd_addr_in       (rd_addr_in),
        .reg_write_in     (reg_write_in),
        .mem_to_reg_in    (mem_to_reg_in),
        .jump_in          (jump_in),
        .mem_read_data_out(mem_read_data_w),
        .alu_result_out   (alu_result_w),
        .pc_plus4_out     (pc_plus4_w),
        .rd_addr_out      (rd_addr_w),
        .reg_write_out    (reg_write_w),
        .mem_to_reg_out   (mem_to_reg_w),
        .jump_out         (jump_w)
    );

    wb_mux u_wb_mux (
        .mem_data   (mem_read_data_w),
        .alu_data   (alu_result_w),
        .pc_plus4   (pc_plus4_w),
        .mem_to_reg (mem_to_reg_w),
        .jump       (jump_w),
        .wb_data    (wb_data_out)
    );

    assign wb_rd_addr_out   = rd_addr_w;
    assign wb_reg_write_out = reg_write_w;

endmodule

mem_wb_stage/tb_mem_wb.v
`timescale 1ns/1ps
//iverilog -o memwb_tb mem_wb.v mem_wb_reg.v wb_mux.v tb_mem_wb.v
//vvp memwb_tb
//gtkwave tb_mem_wb.vcd

`timescale 1ns/1ps

module tb_mem_wb;

    reg         clk;
    reg         rst_n;
    reg [31:0]  mem_read_data_in;
    reg [31:0]  alu_result_in;
    reg [31:0]  pc_plus4_in;
    reg [4:0]   rd_addr_in;
    reg         reg_write_in;
    reg         mem_to_reg_in;
    reg         jump_in;

    wire [31:0] wb_data_out;
    wire [4:0]  wb_rd_addr_out;
    wire        wb_reg_write_out;

    integer errors;

    mem_wb dut (
        .clk              (clk),
        .rst_n            (rst_n),
        .mem_read_data_in (mem_read_data_in),
        .alu_result_in    (alu_result_in),
        .pc_plus4_in      (pc_plus4_in),
        .rd_addr_in       (rd_addr_in),
        .reg_write_in     (reg_write_in),
        .mem_to_reg_in    (mem_to_reg_in),
        .jump_in          (jump_in),
        .wb_data_out      (wb_data_out),
        .wb_rd_addr_out   (wb_rd_addr_out),
        .wb_reg_write_out (wb_reg_write_out)
    );

    initial begin
        clk = 1'b0;
        forever #5 clk = ~clk;
    end

    task check;
        input [31:0] exp_wb_data;
        input [4:0]  exp_rd;
        input        exp_reg_write;
        input [127:0] name;
        begin
            #1;
            if ((wb_data_out !== exp_wb_data) ||
                (wb_rd_addr_out !== exp_rd) ||
                (wb_reg_write_out !== exp_reg_write)) begin
                $display("FAIL : %s", name);
                $display("  mem_read_data_in=%h alu_result_in=%h pc_plus4_in=%h rd_addr_in=%0d",
                         mem_read_data_in, alu_result_in, pc_plus4_in, rd_addr_in);
                $display("  mem_to_reg_in=%b jump_in=%b reg_write_in=%b",
                         mem_to_reg_in, jump_in, reg_write_in);
                $display("  expected wb_data=%h rd=%0d reg_write=%b",
                         exp_wb_data, exp_rd, exp_reg_write);
                $display("  got      wb_data=%h rd=%0d reg_write=%b",
                         wb_data_out, wb_rd_addr_out, wb_reg_write_out);
                errors = errors + 1;
            end
            else begin
                $display("PASS : %s  wb_data=%h", name, wb_data_out);
            end
        end
    endtask

    initial begin
        $dumpfile("tb_mem_wb.vcd");
        $dumpvars(0, tb_mem_wb);

        errors = 0;

        rst_n = 1'b0;
        mem_read_data_in = 32'd0;
        alu_result_in    = 32'd0;
        pc_plus4_in      = 32'd0;
        rd_addr_in       = 5'd0;
        reg_write_in     = 1'b0;
        mem_to_reg_in    = 1'b0;
        jump_in          = 1'b0;

        @(posedge clk);
        @(posedge clk);
        rst_n = 1'b1;

        // ALU path
        mem_read_data_in = 32'hAAAA_AAAA;
        alu_result_in    = 32'h1234_5678;
        pc_plus4_in      = 32'h0000_1004;
        rd_addr_in       = 5'd3;
        reg_write_in     = 1'b1;
        mem_to_reg_in    = 1'b0;
        jump_in          = 1'b0;
        @(posedge clk);
        check(32'h1234_5678, 5'd3, 1'b1, "ALU path");

        // Memory path
        mem_read_data_in = 32'hDEAD_BEEF;
        alu_result_in    = 32'h1111_2222;
        pc_plus4_in      = 32'h0000_1004;
        rd_addr_in       = 5'd5;
        reg_write_in     = 1'b1;
        mem_to_reg_in    = 1'b1;
        jump_in          = 1'b0;
        @(posedge clk);
        check(32'hDEAD_BEEF, 5'd5, 1'b1, "Memory path");

        // Jump path
        mem_read_data_in = 32'h0000_0000;
        alu_result_in    = 32'h3333_4444;
        pc_plus4_in      = 32'h0000_1004;
        rd_addr_in       = 5'd1;
        reg_write_in     = 1'b1;
        mem_to_reg_in    = 1'b0;
        jump_in          = 1'b1;
        @(posedge clk);
        check(32'h0000_1004, 5'd1, 1'b1, "Jump path");

        // reg_write disabled
        mem_read_data_in = 32'hCAFE_BABE;
        alu_result_in    = 32'h5555_6666;
        pc_plus4_in      = 32'h0000_2004;
        rd_addr_in       = 5'd9;
        reg_write_in     = 1'b0;
        mem_to_reg_in    = 1'b0;
        jump_in          = 1'b0;
        @(posedge clk);
        check(32'h5555_6666, 5'd9, 1'b0, "Write disable passthrough");

        if (errors == 0)
            $display("ALL TESTS PASSED");
        else
            $display("TOTAL ERRORS = %0d", errors);

        $finish;
    end

endmodule

mem_wb_stage/tb_mem_wb.vcd
$date
	Sat May 02 21:46:03 2026
$end
$version
	Icarus Verilog
$end
$timescale
	1ps
$end
$scope module tb_mem_wb $end
$var wire 1 ! wb_reg_write_out $end
$var wire 5 " wb_rd_addr_out [4:0] $end
$var wire 32 # wb_data_out [31:0] $end
$var reg 32 $ alu_result_in [31:0] $end
$var reg 1 % clk $end
$var reg 1 & jump_in $end
$var reg 32 ' mem_read_data_in [31:0] $end
$var reg 1 ( mem_to_reg_in $end
$var reg 32 ) pc_plus4_in [31:0] $end
$var reg 5 * rd_addr_in [4:0] $end
$var reg 1 + reg_write_in $end
$var reg 1 , rst_n $end
$var integer 32 - errors [31:0] $end
$scope module dut $end
$var wire 32 . alu_result_in [31:0] $end
$var wire 1 % clk $end
$var wire 1 & jump_in $end
$var wire 32 / mem_read_data_in [31:0] $end
$var wire 1 ( mem_to_reg_in $end
$var wire 32 0 pc_plus4_in [31:0] $end
$var wire 5 1 rd_addr_in [4:0] $end
$var wire 1 + reg_write_in $end
$var wire 1 , rst_n $end
$var wire 5 2 wb_rd_addr_out [4:0] $end
$var wire 1 ! wb_reg_write_out $end
$var wire 32 3 wb_data_out [31:0] $end
$var wire 1 4 reg_write_w $end
$var wire 5 5 rd_addr_w [4:0] $end
$var wire 32 6 pc_plus4_w [31:0] $end
$var wire 1 7 mem_to_reg_w $end
$var wire 32 8 mem_read_data_w [31:0] $end
$var wire 1 9 jump_w $end
$var wire 32 : alu_result_w [31:0] $end
$scope module u_mem_wb_reg $end
$var wire 32 ; alu_result_in [31:0] $end
$var wire 1 % clk $end
$var wire 1 & jump_in $end
$var wire 32 < mem_read_data_in [31:0] $end
$var wire 1 ( mem_to_reg_in $end
$var wire 32 = pc_plus4_in [31:0] $end
$var wire 5 > rd_addr_in [4:0] $end
$var wire 1 + reg_write_in $end
$var wire 1 , rst_n $end
$var reg 32 ? alu_result_out [31:0] $end
$var reg 1 9 jump_out $end
$var reg 32 @ mem_read_data_out [31:0] $end
$var reg 1 7 mem_to_reg_out $end
$var reg 32 A pc_plus4_out [31:0] $end
$var reg 5 B rd_addr_out [4:0] $end
$var reg 1 4 reg_write_out $end
$upscope $end
$scope module u_wb_mux $end
$var wire 32 C alu_data [31:0] $end
$var wire 1 9 jump $end
$var wire 32 D mem_data [31:0] $end
$var wire 1 7 mem_to_reg $end
$var wire 32 E pc_plus4 [31:0] $end
$var reg 32 F wb_data [31:0] $end
$upscope $end
$upscope $end
$scope task check $end
$var reg 5 G exp_rd [4:0] $end
$var reg 1 H exp_reg_write $end
$var reg 32 I exp_wb_data [31:0] $end
$var reg 128 J name [127:0] $end
$upscope $end
$upscope $end
$enddefinitions $end
$comment Show the parameter values. $end
$dumpall
$end
#0
$dumpvars
bx J
bx I
xH
bx G
b0 F
b0 E
b0 D
b0 C
b0 B
b0 A
b0 @
b0 ?
b0 >
b0 =
b0 <
b0 ;
b0 :
09
b0 8
07
b0 6
b0 5
04
b0 3
b0 2
b0 1
b0 0
b0 /
b0 .
b0 -
0,
0+
b0 *
b0 )
0(
b0 '
0&
0%
b0 $
b0 #
b0 "
0!
$end
#5000
1%
#10000
0%
#15000
b10010001101000101011001111000 #
b10010001101000101011001111000 3
b10010001101000101011001111000 F
1!
14
b11 "
b11 2
b11 5
b11 B
b1000000000100 6
b1000000000100 A
b1000000000100 E
b10010001101000101011001111000 :
b10010001101000101011001111000 ?
b10010001101000101011001111000 C
b10101010101010101010101010101010 8
b10101010101010101010101010101010 @
b10101010101010101010101010101010 D
1+
b11 *
b11 1
b11 >
b1000000000100 )
b1000000000100 0
b1000000000100 =
b10010001101000101011001111000 $
b10010001101000101011001111000 .
b10010001101000101011001111000 ;
b10101010101010101010101010101010 '
b10101010101010101010101010101010 /
b10101010101010101010101010101010 <
1,
1%
#20000
0%
#25000
b100000101001100010101010010000001110000011000010111010001101000 J
1H
b11 G
b10010001101000101011001111000 I
1%
#26000
1(
b101 *
b101 1
b101 >
b10001000100010010001000100010 $
b10001000100010010001000100010 .
b10001000100010010001000100010 ;
b11011110101011011011111011101111 '
b11011110101011011011111011101111 /
b11011110101011011011111011101111 <
#30000
0%
#35000
b11011110101011011011111011101111 #
b11011110101011011011111011101111 3
b11011110101011011011111011101111 F
17
b101 "
b101 2
b101 5
b101 B
b10001000100010010001000100010 :
b10001000100010010001000100010 ?
b10001000100010010001000100010 C
b11011110101011011011111011101111 8
b11011110101011011011111011101111 @
b11011110101011011011111011101111 D
b100110101100101011011010110111101110010011110010010000001110000011000010111010001101000 J
b101 G
b11011110101011011011111011101111 I
1%
#36000
1&
0(
b1 *
b1 1
b1 >
b110011001100110100010001000100 $
b110011001100110100010001000100 .
b110011001100110100010001000100 ;
b0 '
b0 /
b0 <
#40000
0%
#45000
b1000000000100 #
b1000000000100 3
b1000000000100 F
19
07
b1 "
b1 2
b1 5
b1 B
b110011001100110100010001000100 :
b110011001100110100010001000100 ?
b110011001100110100010001000100 C
b0 8
b0 @
b0 D
b10010100111010101101101011100000010000001110000011000010111010001101000 J
b1 G
b1000000000100 I
1%
#46000
0&
0+
b1001 *
b1001 1
b1001 >
b10000000000100 )
b10000000000100 0
b10000000000100 =
b1010101010101010110011001100110 $
b1010101010101010110011001100110 .
b1010101010101010110011001100110 ;
b11001010111111101011101010111110 '
b11001010111111101011101010111110 /
b11001010111111101011101010111110 <
#50000
0%
#55000
b1010101010101010110011001100110 #
b1010101010101010110011001100110 3
b1010101010101010110011001100110 F
09
0!
04
b1001 "
b1001 2
b1001 5
b1001 B
b10000000000100 6
b10000000000100 A
b10000000000100 E
b1010101010101010110011001100110 :
b1010101010101010110011001100110 ?
b1010101010101010110011001100110 C
b11001010111111101011101010111110 8
b11001010111111101011101010111110 @
b11001010111111101011101010111110 D
b1100001011000100110110001100101001000000111000001100001011100110111001101110100011010000111001001101111011101010110011101101000 J
0H
b1001 G
b1010101010101010110011001100110 I
1%
