decode_execute/riscv_defines.vh

//opcode macros
//funct3 macros
//funct7 macros
//ALU operation macros
//writeback select macros
//immediate type macros
//FFT custom instruction macros
`ifndef RISCV_DEFINES_VH
`define RISCV_DEFINES_VH

// ============================================================
// Basic architectural parameters
// ============================================================
`define XLEN           32
`define REG_ADDR_W     5
`define INSTR_W        32
`define DATA_W         32
`define IMEM_DEPTH     1024
`define DMEM_DEPTH     1024
`define RESET_PC             0
// ============================================================
// RV32I opcodes
// ============================================================
`define OPCODE_OP      7'b0110011   // R-type
`define OPCODE_OP_IMM  7'b0010011   // I-type ALU
`define OPCODE_LOAD    7'b0000011   // LW
`define OPCODE_STORE   7'b0100011   // SW
`define OPCODE_BRANCH  7'b1100011   // BEQ/BNE
`define OPCODE_JAL     7'b1101111   // JAL

// ============================================================
// Custom opcode space for FFT instruction
// custom-0 opcode
// ============================================================
`define OPCODE_FFT     7'b0001011

// ============================================================
// funct3 values
// ============================================================
`define FUNCT3_ADD_SUB 3'b000
`define FUNCT3_XOR     3'b100
`define FUNCT3_OR      3'b110
`define FUNCT3_AND     3'b111

`define FUNCT3_ADDI    3'b000

`define FUNCT3_LW      3'b010
`define FUNCT3_SW      3'b010

`define FUNCT3_BEQ     3'b000
`define FUNCT3_BNE     3'b001

// ============================================================
// funct7 values
// ============================================================
`define FUNCT7_ADD     7'b0000000
`define FUNCT7_SUB     7'b0100000
`define FUNCT7_LOGIC   7'b0000000

// ============================================================
// FFT custom instruction fields
// Example: FFT_BLY rd, rs1, rs2
// ============================================================
`define FUNCT3_FFT_BLY 3'b000
`define FUNCT7_FFT_BLY 7'b0000001

// ============================================================
// ALU operation select
// ============================================================
`define ALU_ADD        4'd0
`define ALU_SUB        4'd1
`define ALU_AND        4'd2
`define ALU_OR         4'd3
`define ALU_XOR        4'd4
`define ALU_PASS       4'd5

// ============================================================
// Writeback select
// ============================================================
`define WB_ALU         2'd0
`define WB_MEM         2'd1
`define WB_PC4         2'd2
`define WB_FFT         2'd3

// ============================================================
// Immediate type select
// ============================================================
`define IMM_I          3'd0
`define IMM_S          3'd1
`define IMM_B          3'd2
`define IMM_J          3'd3
`define IMM_NONE       3'd4

`endif

fetch_stage/instr_mem.v
`include "riscv_defines.vh"
//`include "../riscv_defines.vh"



/*
------------------------------------------------------------------------------
File        : instr_mem.v
Module      : instr_mem
Purpose     : Synthesizable instruction ROM for baseline RV32I fetch stage

Functionality:
- Stores 32-bit instructions as fixed ROM contents
- Provides combinational instruction fetch using current PC
- Uses word-aligned addressing with pc_in[31:2]

Major inputs:
- pc_in         : Current Program Counter from fetch stage

Major outputs:
- instr_out     : 32-bit fetched instruction

Notes:
- Pure combinational ROM model
- No initial block, no $readmemh
- Suitable for stricter synthesizable RTL coding style
- Lower 2 bits of PC are ignored because instructions are 32-bit aligned
- Unused addresses return 32'h0000_0000
- Replace ROM contents below with your actual program instructions
------------------------------------------------------------------------------
*/

module instr_mem (
    input  [`XLEN-1:0] pc_in,
    output reg [31:0]  instr_out
);

    wire [`XLEN-1:0] word_addr;
    assign word_addr = pc_in >> 2;

//    always @(*) begin
//        case (word_addr)
//            32'd0: instr_out = 32'h00A00093; // addi x1, x0, 10
//            32'd1: instr_out = 32'h01400113; // addi x2, x0, 20
//            32'd2: instr_out = 32'h002081B3; // add  x3, x1, x2
//            32'd3: instr_out = 32'h40310233; // sub  x4, x2, x3
//            32'd4: instr_out = 32'h00302023; // sw   x3, 0(x0)
//            32'd5: instr_out = 32'h00002283; // lw   x5, 0(x0)
//            32'd6: instr_out = 32'h00328463; // beq  x5, x3, +8
//            32'd7: instr_out = 32'h00100313; // addi x6, x0, 1
//            32'd8: instr_out = 32'h0000006F; // jal  x0, 0
//            default: instr_out = 32'h00000000;
//        endcase
//    end
always @(*) begin
    case (word_addr)
        32'd0: instr_out = 32'h002081B3; // ADD  x3, x1, x2  (002081B3)
        32'd1: instr_out = 32'h402081B3; // SUB  x3, x1, x2  (402081B3)
        32'd2: instr_out = 32'h0020F1B3; // AND  x3, x1, x2  (0020F1B3)
        32'd3: instr_out = 32'h0020E1B3; // OR   x3, x1, x2  (0020E1B3)
        32'd4: instr_out = 32'h0020C1B3; // XOR  x3, x1, x2  (0020C1B3)
        32'd5: instr_out = 32'h00A02083; // LW   x1, 0(x0)  (00A02083)
        32'd6: instr_out = 32'h00302023; // SW   x3, 0(x0)  (00302023)
        32'd7: instr_out = 32'h00208463; // BEQ  x1, x2, +8 (00208463)
        32'd8: instr_out = 32'h00209463; // BNE  x1, x2, +8 (00209463)
        32'd9: instr_out = 32'h0000006F; // JAL  x0, 0      (0000006F)
        32'd10: instr_out = 32'h020000BB; // FFT  x0, x4, x4 (020000BB)
        default: instr_out = 32'h0000006F; 
    endcase
end


endmodule

fetch_stage/pc_reg.v
//`include "../riscv_defines.vh"
`include "riscv_defines.vh"

/*
------------------------------------------------------------------------------
File        : pc_reg.v
Module      : pc_reg
Purpose     : Program Counter register for baseline RV32I datapath

Functionality:
- Holds the current Program Counter (PC)
- Updates PC on every clock edge
- Supports reset, stall, and next-PC loading
- Used by instruction fetch stage

Major inputs:
- clk        : Clock input
- rst_n      : Active-low reset
- stall      : Holds current PC when asserted
- next_pc    : Next PC value to be loaded

Major outputs:
- pc_out     : Current PC value

Notes:
- Sequential logic block
- On reset, PC is initialized to RESET_PC
- If stall = 1, current PC is retained
- Otherwise, PC is updated with next_pc
- Written in Verilog-only style for Icarus compatibility

Run note:
- This is an RTL module, so it is compiled together with its testbench
------------------------------------------------------------------------------
*/

//module pc_reg (
//    input                  clk,
//    input                  rst_n,
//    input                  stall,
//    input  [31:0]     next_pc,
//    output reg [31:0] pc_out
//);
//
//    always @(posedge clk or negedge rst_n) begin
//        if (!rst_n)
//          //  pc_out <= `RESET_PC;
//pc_out <= 32'h0000_1000; 
//        else if (stall)
//            pc_out <= pc_out;
//        else
//            pc_out <= next_pc;
//    end
//
//endmodule
`timescale 1ns/1ps

module pc_reg (
    input  wire        clk,
    input  wire        rst_n,
    input  wire        stall,
    input  wire [31:0] next_pc,
    output reg  [31:0] pc_out
);

    always @(posedge clk or negedge rst_n) begin
        if (!rst_n)
            pc_out <= 32'h0000_1000;
        else if (!stall)
            pc_out <= next_pc;
    end

endmodule

fetch_stage/fetch_stage.v
//`include "pc_reg.v"
//`include "instr_mem.v"
`timescale 1ns/1ps

module fetch_stage (
    input  wire        clk,
    input  wire        rst_n,
    input  wire        stall,
    input  wire        branch_taken,
    input  wire [31:0] branch_target,
    output wire [31:0] pc_out,
    output wire [31:0] instr_out,
    output wire [31:0] pc_plus4_out
);

    wire [31:0] pc_current;
    wire [31:0] pc_next;

    assign pc_next     = branch_taken ? branch_target : (pc_current + 32'd4);
    assign pc_plus4_out = pc_current + 32'd4;

    pc_reg u_pc_reg (
        .clk     (clk),
        .rst_n   (rst_n),
        .stall   (stall),
        .next_pc (pc_next),
        .pc_out  (pc_current)
    );

    instr_mem u_instr_mem (
        .pc_in     (pc_current),
        .instr_out (instr_out)
    );

    assign pc_out = pc_current;

endmodule

fetch_stage/tb_fetch_stage.v
//iverilog -o fetch_tb fetch_stage.v tb_fetch_stage.v
//vvp fetch_tb
//gtkwave tb_fetch_stage.vcd
//iverilog -o fetch_tb fetch_stage.v pc_reg.v instr_mem.v tb_fetch_stage.v
//vvp fetch_tb
`timescale 1ns/1ps
//`include fetch_stage.v
module tb_fetch_stage;

    reg clk;
    reg rst_n;
    reg stall;
    reg branch_taken;
    reg [31:0] branch_target;

    wire [31:0] pc_out;
    wire [31:0] instr_out;
    wire [31:0] pc_plus4_out;

    integer errors;

    fetch_stage uut (
        .clk(clk),
        .rst_n(rst_n),
        .stall(stall),
        .branch_taken(branch_taken),
        .branch_target(branch_target),
        .pc_out(pc_out),
        .instr_out(instr_out),
        .pc_plus4_out(pc_plus4_out)
    );

    always #5 clk = ~clk;

    task check;
        input [31:0] exp_pc;
        input [31:0] exp_pc_plus4;
        input [127:0] test_name;
        begin
            #1;
            if (pc_out !== exp_pc || pc_plus4_out !== exp_pc_plus4) begin
                $display("FAIL : %s", test_name);
                $display("       pc_out       = %h  expected = %h", pc_out, exp_pc);
                $display("       pc_plus4_out = %h  expected = %h", pc_plus4_out, exp_pc_plus4);
                errors = errors + 1;
            end
            else begin
                $display("PASS : %s", test_name);
            end
        end
    endtask

    initial begin
        $dumpfile("tb_fetch_stage.vcd");
        $dumpvars(0, tb_fetch_stage);

        clk = 0;
        rst_n = 0;
        stall = 0;
        branch_taken = 0;
        branch_target = 32'h0000_0000;
        errors = 0;

        // Reset check
        #12;
        check(32'h0000_0000, 32'h0000_0004, "RESET_CHECK");

        rst_n = 1;

        // PC should increment by 4 each cycle
        @(posedge clk);
        check(32'h0000_0004, 32'h0000_0008, "PC_PLUS4_1");

        @(posedge clk);
        check(32'h0000_0008, 32'h0000_000C, "PC_PLUS4_2");

        @(posedge clk);
        check(32'h0000_000C, 32'h0000_0010, "PC_PLUS4_3");

        // Stall should hold PC
        stall = 1;
        @(posedge clk);
        check(32'h0000_000C, 32'h0000_0010, "STALL_HOLD_1");

        @(posedge clk);
        check(32'h0000_000C, 32'h0000_0010, "STALL_HOLD_2");

        stall = 0;

        // Branch should redirect PC
        branch_taken = 1;
        branch_target = 32'h0000_0040;
        @(posedge clk);
        check(32'h0000_0040, 32'h0000_0044, "BRANCH_REDIRECT");

        branch_taken = 0;
        @(posedge clk);
        check(32'h0000_0044, 32'h0000_0048, "POST_BRANCH_INCREMENT");

        if (errors == 0)
            $display("\nALL FETCH_STAGE TESTS PASSED\n");
        else
            $display("\nFETCH_STAGE TESTS FAILED : total errors = %0d\n", errors);

         #1000; $finish;
    end

endmodule

fetch_stage/tb_fetch_stage.vcd
$date
	Wed Apr 22 21:31:35 2026
$end
$version
	Icarus Verilog
$end
$timescale
	1ps
$end
$scope module tb_fetch_stage $end
$var wire 32 ! pc_plus4_out [31:0] $end
$var wire 32 " pc_out [31:0] $end
$var wire 32 # instr_out [31:0] $end
$var reg 1 $ branch_taken $end
$var reg 32 % branch_target [31:0] $end
$var reg 1 & clk $end
$var reg 1 ' rst_n $end
$var reg 1 ( stall $end
$var integer 32 ) errors [31:0] $end
$scope module uut $end
$var wire 1 $ branch_taken $end
$var wire 32 * branch_target [31:0] $end
$var wire 1 & clk $end
$var wire 32 + pc_out [31:0] $end
$var wire 1 ' rst_n $end
$var wire 1 ( stall $end
$var wire 32 , pc_plus4_out [31:0] $end
$var wire 32 - pc_next [31:0] $end
$var wire 32 . pc_current [31:0] $end
$var wire 32 / instr_out [31:0] $end
$scope module u_instr_mem $end
$var wire 32 0 word_addr [31:0] $end
$var wire 32 1 pc_in [31:0] $end
$var reg 32 2 instr_out [31:0] $end
$upscope $end
$scope module u_pc_reg $end
$var wire 1 & clk $end
$var wire 32 3 next_pc [31:0] $end
$var wire 1 ' rst_n $end
$var wire 1 4 stall $end
$var reg 32 5 pc_out [31:0] $end
$upscope $end
$upscope $end
$scope task check $end
$var reg 32 6 exp_pc [31:0] $end
$var reg 32 7 exp_pc_plus4 [31:0] $end
$var reg 128 8 test_name [127:0] $end
$upscope $end
$upscope $end
$enddefinitions $end
$comment Show the parameter values. $end
$dumpall
$end
#0
$dumpvars
bx 8
bx 7
bx 6
b0 5
z4
b100 3
b101000000000000010010011 2
b0 1
b0 0
b101000000000000010010011 /
b0 .
b100 -
b100 ,
b0 +
b0 *
b0 )
0(
0'
0&
b0 %
0$
b101000000000000010010011 #
b0 "
b100 !
$end
#5000
1&
#10000
0&
#12000
b101001001000101010100110100010101010100010111110100001101001000010001010100001101001011 8
b100 7
b0 6
#13000
1'
#15000
b1010000000000000100010011 #
b1010000000000000100010011 /
b1010000000000000100010011 2
b1000 3
b1 0
b1000 -
b1000 !
b1000 ,
b100 "
b100 +
b100 .
b100 1
b100 5
b1010000010000110101111101010000010011000101010101010011001101000101111100110001 8
b1000 7
b100 6
1&
#20000
0&
#25000
b1000001000000110110011 #
b1000001000000110110011 /
b1000001000000110110011 2
b1100 3
b10 0
b1100 -
b1100 !
b1100 ,
b1000 "
b1000 +
b1000 .
b1000 1
b1000 5
b1010000010000110101111101010000010011000101010101010011001101000101111100110010 8
b1100 7
b1000 6
1&
#30000
0&
#35000
b1000000001100010000001000110011 #
b1000000001100010000001000110011 /
b1000000001100010000001000110011 2
b10000 3
b11 0
b10000 -
b10000 !
b10000 ,
b1100 "
b1100 +
b1100 .
b1100 1
b1100 5
b1010000010000110101111101010000010011000101010101010011001101000101111100110011 8
b10000 7
b1100 6
1&
#36000
b1100 3
1(
#40000
0&
#45000
b10100110101010001000001010011000100110001011111010010000100111101001100010001000101111100110001 8
1&
#50000
0&
#55000
b10100110101010001000001010011000100110001011111010010000100111101001100010001000101111100110010 8
1&
#56000
b1000000 -
b1000000 3
b1000000 %
b1000000 *
1$
0(
#60000
0&
#65000
b0 #
b0 /
b0 2
b10000 0
b1000100 !
b1000100 ,
b1000000 "
b1000000 +
b1000000 .
b1000000 1
b1000000 5
b10000100101001001000001010011100100001101001000010111110101001001000101010001000100100101010010010001010100001101010100 8
b1000100 7
b1000000 6
1&
#66000
b1000100 3
b1000100 -
0$
#70000
0&
#75000
b1001000 3
b10001 0
b1001000 -
b1001000 !
b1001000 ,
b1000100 "
b1000100 +
b1000100 .
b1000100 1
b1000100 5
b1000010010100100100000101001110010000110100100001011111010010010100111001000011010100100100010101001101010001010100111001010100 8
b1001000 7
b1000100 6
1&
#80000
0&
#85000
b1001100 3
b10010 0
b1001100 -
b1001100 !
b1001100 ,
b1001000 "
b1001000 +
b1001000 .
b1001000 1
b1001000 5
1&
#90000
0&
#95000
b1010000 3
b10011 0
b1010000 -
b1010000 !
b1010000 ,
b1001100 "
b1001100 +
b1001100 .
b1001100 1
b1001100 5
1&
#100000
0&
#105000
b1010100 3
b10100 0
b1010100 -
b1010100 !
b1010100 ,
b1010000 "
b1010000 +
b1010000 .
b1010000 1
b1010000 5
1&
#110000
0&
#115000
b1011000 3
b10101 0
b1011000 -
b1011000 !
b1011000 ,
b1010100 "
b1010100 +
b1010100 .
b1010100 1
b1010100 5
1&
#120000
0&
#125000
b1011100 3
b10110 0
b1011100 -
b1011100 !
b1011100 ,
b1011000 "
b1011000 +
b1011000 .
b1011000 1
b1011000 5
1&
#130000
0&
#135000
b1100000 3
b10111 0
b1100000 -
b1100000 !
b1100000 ,
b1011100 "
b1011100 +
b1011100 .
b1011100 1
b1011100 5
1&
#140000
0&
#145000
b1100100 3
b11000 0
b1100100 -
b1100100 !
b1100100 ,
b1100000 "
b1100000 +
b1100000 .
b1100000 1
b1100000 5
1&
#150000
0&
#155000
b1101000 3
b11001 0
b1101000 -
b1101000 !
b1101000 ,
b1100100 "
b1100100 +
b1100100 .
b1100100 1
b1100100 5
1&
#160000
0&
#165000
b1101100 3
b11010 0
b1101100 -
b1101100 !
b1101100 ,
b1101000 "
b1101000 +
b1101000 .
b1101000 1
b1101000 5
1&
#170000
0&
#175000
b1110000 3
b11011 0
b1110000 -
b1110000 !
b1110000 ,
b1101100 "
b1101100 +
b1101100 .
b1101100 1
b1101100 5
1&
#180000
0&
#185000
b1110100 3
b11100 0
b1110100 -
b1110100 !
b1110100 ,
b1110000 "
b1110000 +
b1110000 .
b1110000 1
b1110000 5
1&
#190000
0&
#195000
b1111000 3
b11101 0
b1111000 -
b1111000 !
b1111000 ,
b1110100 "
b1110100 +
b1110100 .
b1110100 1
b1110100 5
1&
#200000
0&
#205000
b1111100 3
b11110 0
b1111100 -
b1111100 !
b1111100 ,
b1111000 "
b1111000 +
b1111000 .
b1111000 1
b1111000 5
1&
#210000
0&
#215000
b10000000 3
b11111 0
b10000000 -
b10000000 !
b10000000 ,
b1111100 "
b1111100 +
b1111100 .
b1111100 1
b1111100 5
1&
#220000
0&
#225000
b10000100 3
b100000 0
b10000100 -
b10000100 !
b10000100 ,
b10000000 "
b10000000 +
b10000000 .
b10000000 1
b10000000 5
1&
#230000
0&
#235000
b10001000 3
b100001 0
b10001000 -
b10001000 !
b10001000 ,
b10000100 "
b10000100 +
b10000100 .
b10000100 1
b10000100 5
1&
#240000
0&
#245000
b10001100 3
b100010 0
b10001100 -
b10001100 !
b10001100 ,
b10001000 "
b10001000 +
b10001000 .
b10001000 1
b10001000 5
1&
#250000
0&
#255000
b10010000 3
b100011 0
b10010000 -
b10010000 !
b10010000 ,
b10001100 "
b10001100 +
b10001100 .
b10001100 1
b10001100 5
1&
#260000
0&
#265000
b10010100 3
b100100 0
b10010100 -
b10010100 !
b10010100 ,
b10010000 "
b10010000 +
b10010000 .
b10010000 1
b10010000 5
1&
#270000
0&
#275000
b10011000 3
b100101 0
b10011000 -
b10011000 !
b10011000 ,
b10010100 "
b10010100 +
b10010100 .
b10010100 1
b10010100 5
1&
#280000
0&
#285000
b10011100 3
b100110 0
b10011100 -
b10011100 !
b10011100 ,
b10011000 "
b10011000 +
b10011000 .
b10011000 1
b10011000 5
1&
#290000
0&
#295000
b10100000 3
b100111 0
b10100000 -
b10100000 !
b10100000 ,
b10011100 "
b10011100 +
b10011100 .
b10011100 1
b10011100 5
1&
#300000
0&
#305000
b10100100 3
b101000 0
b10100100 -
b10100100 !
b10100100 ,
b10100000 "
b10100000 +
b10100000 .
b10100000 1
b10100000 5
1&
#310000
0&
#315000
b10101000 3
b101001 0
b10101000 -
b10101000 !
b10101000 ,
b10100100 "
b10100100 +
b10100100 .
b10100100 1
b10100100 5
1&
#320000
0&
#325000
b10101100 3
b101010 0
b10101100 -
b10101100 !
b10101100 ,
b10101000 "
b10101000 +
b10101000 .
b10101000 1
b10101000 5
1&
#330000
0&
#335000
b10110000 3
b101011 0
b10110000 -
b10110000 !
b10110000 ,
b10101100 "
b10101100 +
b10101100 .
b10101100 1
b10101100 5
1&
#340000
0&
#345000
b10110100 3
b101100 0
b10110100 -
b10110100 !
b10110100 ,
b10110000 "
b10110000 +
b10110000 .
b10110000 1
b10110000 5
1&
#350000
0&
#355000
b10111000 3
b101101 0
b10111000 -
b10111000 !
b10111000 ,
b10110100 "
b10110100 +
b10110100 .
b10110100 1
b10110100 5
1&
#360000
0&
#365000
b10111100 3
b101110 0
b10111100 -
b10111100 !
b10111100 ,
b10111000 "
b10111000 +
b10111000 .
b10111000 1
b10111000 5
1&
#370000
0&
#375000
b11000000 3
b101111 0
b11000000 -
b11000000 !
b11000000 ,
b10111100 "
b10111100 +
b10111100 .
b10111100 1
b10111100 5
1&
#380000
0&
#385000
b11000100 3
b110000 0
b11000100 -
b11000100 !
b11000100 ,
b11000000 "
b11000000 +
b11000000 .
b11000000 1
b11000000 5
1&
#390000
0&
#395000
b11001000 3
b110001 0
b11001000 -
b11001000 !
b11001000 ,
b11000100 "
b11000100 +
b11000100 .
b11000100 1
b11000100 5
1&
#400000
0&
#405000
b11001100 3
b110010 0
b11001100 -
b11001100 !
b11001100 ,
b11001000 "
b11001000 +
b11001000 .
b11001000 1
b11001000 5
1&
#410000
0&
#415000
b11010000 3
b110011 0
b11010000 -
b11010000 !
b11010000 ,
b11001100 "
b11001100 +
b11001100 .
b11001100 1
b11001100 5
1&
#420000
0&
#425000
b11010100 3
b110100 0
b11010100 -
b11010100 !
b11010100 ,
b11010000 "
b11010000 +
b11010000 .
b11010000 1
b11010000 5
1&
#430000
0&
#435000
b11011000 3
b110101 0
b11011000 -
b11011000 !
b11011000 ,
b11010100 "
b11010100 +
b11010100 .
b11010100 1
b11010100 5
1&
#440000
0&
#445000
b11011100 3
b110110 0
b11011100 -
b11011100 !
b11011100 ,
b11011000 "
b11011000 +
b11011000 .
b11011000 1
b11011000 5
1&
#450000
0&
#455000
b11100000 3
b110111 0
b11100000 -
b11100000 !
b11100000 ,
b11011100 "
b11011100 +
b11011100 .
b11011100 1
b11011100 5
1&
#460000
0&
#465000
b11100100 3
b111000 0
b11100100 -
b11100100 !
b11100100 ,
b11100000 "
b11100000 +
b11100000 .
b11100000 1
b11100000 5
1&
#470000
0&
#475000
b11101000 3
b111001 0
b11101000 -
b11101000 !
b11101000 ,
b11100100 "
b11100100 +
b11100100 .
b11100100 1
b11100100 5
1&
#480000
0&
#485000
b11101100 3
b111010 0
b11101100 -
b11101100 !
b11101100 ,
b11101000 "
b11101000 +
b11101000 .
b11101000 1
b11101000 5
1&
#490000
0&
#495000
b11110000 3
b111011 0
b11110000 -
b11110000 !
b11110000 ,
b11101100 "
b11101100 +
b11101100 .
b11101100 1
b11101100 5
1&
#500000
0&
#505000
b11110100 3
b111100 0
b11110100 -
b11110100 !
b11110100 ,
b11110000 "
b11110000 +
b11110000 .
b11110000 1
b11110000 5
1&
#510000
0&
#515000
b11111000 3
b111101 0
b11111000 -
b11111000 !
b11111000 ,
b11110100 "
b11110100 +
b11110100 .
b11110100 1
b11110100 5
1&
#520000
0&
#525000
b11111100 3
b111110 0
b11111100 -
b11111100 !
b11111100 ,
b11111000 "
b11111000 +
b11111000 .
b11111000 1
b11111000 5
1&
#530000
0&
#535000
b100000000 3
b111111 0
b100000000 -
b100000000 !
b100000000 ,
b11111100 "
b11111100 +
b11111100 .
b11111100 1
b11111100 5
1&
#540000
0&
#545000
b100000100 3
b1000000 0
b100000100 -
b100000100 !
b100000100 ,
b100000000 "
b100000000 +
b100000000 .
b100000000 1
b100000000 5
1&
#550000
0&
#555000
b100001000 3
b1000001 0
b100001000 -
b100001000 !
b100001000 ,
b100000100 "
b100000100 +
b100000100 .
b100000100 1
b100000100 5
1&
#560000
0&
#565000
b100001100 3
b1000010 0
b100001100 -
b100001100 !
b100001100 ,
b100001000 "
b100001000 +
b100001000 .
b100001000 1
b100001000 5
1&
#570000
0&
#575000
b100010000 3
b1000011 0
b100010000 -
b100010000 !
b100010000 ,
b100001100 "
b100001100 +
b100001100 .
b100001100 1
b100001100 5
1&
#580000
0&
#585000
b100010100 3
b1000100 0
b100010100 -
b100010100 !
b100010100 ,
b100010000 "
b100010000 +
b100010000 .
b100010000 1
b100010000 5
1&
#590000
0&
#595000
b100011000 3
b1000101 0
b100011000 -
b100011000 !
b100011000 ,
b100010100 "
b100010100 +
b100010100 .
b100010100 1
b100010100 5
1&
#600000
0&
#605000
b100011100 3
b1000110 0
b100011100 -
b100011100 !
b100011100 ,
b100011000 "
b100011000 +
b100011000 .
b100011000 1
b100011000 5
1&
#610000
0&
#615000
b100100000 3
b1000111 0
b100100000 -
b100100000 !
b100100000 ,
b100011100 "
b100011100 +
b100011100 .
b100011100 1
b100011100 5
1&
#620000
0&
#625000
b100100100 3
b1001000 0
b100100100 -
b100100100 !
b100100100 ,
b100100000 "
b100100000 +
b100100000 .
b100100000 1
b100100000 5
1&
#630000
0&
#635000
b100101000 3
b1001001 0
b100101000 -
b100101000 !
b100101000 ,
b100100100 "
b100100100 +
b100100100 .
b100100100 1
b100100100 5
1&
#640000
0&
#645000
b100101100 3
b1001010 0
b100101100 -
b100101100 !
b100101100 ,
b100101000 "
b100101000 +
b100101000 .
b100101000 1
b100101000 5
1&
#650000
0&
#655000
b100110000 3
b1001011 0
b100110000 -
b100110000 !
b100110000 ,
b100101100 "
b100101100 +
b100101100 .
b100101100 1
b100101100 5
1&
#660000
0&
#665000
b100110100 3
b1001100 0
b100110100 -
b100110100 !
b100110100 ,
b100110000 "
b100110000 +
b100110000 .
b100110000 1
b100110000 5
1&
#670000
0&
#675000
b100111000 3
b1001101 0
b100111000 -
b100111000 !
b100111000 ,
b100110100 "
b100110100 +
b100110100 .
b100110100 1
b100110100 5
1&
#680000
0&
#685000
b100111100 3
b1001110 0
b100111100 -
b100111100 !
b100111100 ,
b100111000 "
b100111000 +
b100111000 .
b100111000 1
b100111000 5
1&
#690000
0&
#695000
b101000000 3
b1001111 0
b101000000 -
b101000000 !
b101000000 ,
b100111100 "
b100111100 +
b100111100 .
b100111100 1
b100111100 5
1&
#700000
0&
#705000
b101000100 3
b1010000 0
b101000100 -
b101000100 !
b101000100 ,
b101000000 "
b101000000 +
b101000000 .
b101000000 1
b101000000 5
1&
#710000
0&
#715000
b101001000 3
b1010001 0
b101001000 -
b101001000 !
b101001000 ,
b101000100 "
b101000100 +
b101000100 .
b101000100 1
b101000100 5
1&
#720000
0&
#725000
b101001100 3
b1010010 0
b101001100 -
b101001100 !
b101001100 ,
b101001000 "
b101001000 +
b101001000 .
b101001000 1
b101001000 5
1&
#730000
0&
#735000
b101010000 3
b1010011 0
b101010000 -
b101010000 !
b101010000 ,
b101001100 "
b101001100 +
b101001100 .
b101001100 1
b101001100 5
1&
#740000
0&
#745000
b101010100 3
b1010100 0
b101010100 -
b101010100 !
b101010100 ,
b101010000 "
b101010000 +
b101010000 .
b101010000 1
b101010000 5
1&
#750000
0&
#755000
b101011000 3
b1010101 0
b101011000 -
b101011000 !
b101011000 ,
b101010100 "
b101010100 +
b101010100 .
b101010100 1
b101010100 5
1&
#760000
0&
#765000
b101011100 3
b1010110 0
b101011100 -
b101011100 !
b101011100 ,
b101011000 "
b101011000 +
b101011000 .
b101011000 1
b101011000 5
1&
#770000
0&
#775000
b101100000 3
b1010111 0
b101100000 -
b101100000 !
b101100000 ,
b101011100 "
b101011100 +
b101011100 .
b101011100 1
b101011100 5
1&
#780000
0&
#785000
b101100100 3
b1011000 0
b101100100 -
b101100100 !
b101100100 ,
b101100000 "
b101100000 +
b101100000 .
b101100000 1
b101100000 5
1&
#790000
0&
#795000
b101101000 3
b1011001 0
b101101000 -
b101101000 !
b101101000 ,
b101100100 "
b101100100 +
b101100100 .
b101100100 1
b101100100 5
1&
#800000
0&
#805000
b101101100 3
b1011010 0
b101101100 -
b101101100 !
b101101100 ,
b101101000 "
b101101000 +
b101101000 .
b101101000 1
b101101000 5
1&
#810000
0&
#815000
b101110000 3
b1011011 0
b101110000 -
b101110000 !
b101110000 ,
b101101100 "
b101101100 +
b101101100 .
b101101100 1
b101101100 5
1&
#820000
0&
#825000
b101110100 3
b1011100 0
b101110100 -
b101110100 !
b101110100 ,
b101110000 "
b101110000 +
b101110000 .
b101110000 1
b101110000 5
1&
#830000
0&
#835000
b101111000 3
b1011101 0
b101111000 -
b101111000 !
b101111000 ,
b101110100 "
b101110100 +
b101110100 .
b101110100 1
b101110100 5
1&
#840000
0&
#845000
b101111100 3
b1011110 0
b101111100 -
b101111100 !
b101111100 ,
b101111000 "
b101111000 +
b101111000 .
b101111000 1
b101111000 5
1&
#850000
0&
#855000
b110000000 3
b1011111 0
b110000000 -
b110000000 !
b110000000 ,
b101111100 "
b101111100 +
b101111100 .
b101111100 1
b101111100 5
1&
#860000
0&
#865000
b110000100 3
b1100000 0
b110000100 -
b110000100 !
b110000100 ,
b110000000 "
b110000000 +
b110000000 .
b110000000 1
b110000000 5
1&
#870000
0&
#875000
b110001000 3
b1100001 0
b110001000 -
b110001000 !
b110001000 ,
b110000100 "
b110000100 +
b110000100 .
b110000100 1
b110000100 5
1&
#880000
0&
#885000
b110001100 3
b1100010 0
b110001100 -
b110001100 !
b110001100 ,
b110001000 "
b110001000 +
b110001000 .
b110001000 1
b110001000 5
1&
#890000
0&
#895000
b110010000 3
b1100011 0
b110010000 -
b110010000 !
b110010000 ,
b110001100 "
b110001100 +
b110001100 .
b110001100 1
b110001100 5
1&
#900000
0&
#905000
b110010100 3
b1100100 0
b110010100 -
b110010100 !
b110010100 ,
b110010000 "
b110010000 +
b110010000 .
b110010000 1
b110010000 5
1&
#910000
0&
#915000
b110011000 3
b1100101 0
b110011000 -
b110011000 !
b110011000 ,
b110010100 "
b110010100 +
b110010100 .
b110010100 1
b110010100 5
1&
#920000
0&
#925000
b110011100 3
b1100110 0
b110011100 -
b110011100 !
b110011100 ,
b110011000 "
b110011000 +
b110011000 .
b110011000 1
b110011000 5
1&
#930000
0&
#935000
b110100000 3
b1100111 0
b110100000 -
b110100000 !
b110100000 ,
b110011100 "
b110011100 +
b110011100 .
b110011100 1
b110011100 5
1&
#940000
0&
#945000
b110100100 3
b1101000 0
b110100100 -
b110100100 !
b110100100 ,
b110100000 "
b110100000 +
b110100000 .
b110100000 1
b110100000 5
1&
#950000
0&
#955000
b110101000 3
b1101001 0
b110101000 -
b110101000 !
b110101000 ,
b110100100 "
b110100100 +
b110100100 .
b110100100 1
b110100100 5
1&
#960000
0&
#965000
b110101100 3
b1101010 0
b110101100 -
b110101100 !
b110101100 ,
b110101000 "
b110101000 +
b110101000 .
b110101000 1
b110101000 5
1&
#970000
0&
#975000
b110110000 3
b1101011 0
b110110000 -
b110110000 !
b110110000 ,
b110101100 "
b110101100 +
b110101100 .
b110101100 1
b110101100 5
1&
#980000
0&
#985000
b110110100 3
b1101100 0
b110110100 -
b110110100 !
b110110100 ,
b110110000 "
b110110000 +
b110110000 .
b110110000 1
b110110000 5
1&
#990000
0&
#995000
b110111000 3
b1101101 0
b110111000 -
b110111000 !
b110111000 ,
b110110100 "
b110110100 +
b110110100 .
b110110100 1
b110110100 5
1&
#1000000
0&
#1005000
b110111100 3
b1101110 0
b110111100 -
b110111100 !
b110111100 ,
b110111000 "
b110111000 +
b110111000 .
b110111000 1
b110111000 5
1&
#1010000
0&
#1015000
b111000000 3
b1101111 0
b111000000 -
b111000000 !
b111000000 ,
b110111100 "
b110111100 +
b110111100 .
b110111100 1
b110111100 5
1&
#1020000
0&
#1025000
b111000100 3
b1110000 0
b111000100 -
b111000100 !
b111000100 ,
b111000000 "
b111000000 +
b111000000 .
b111000000 1
b111000000 5
1&
#1030000
0&
#1035000
b111001000 3
b1110001 0
b111001000 -
b111001000 !
b111001000 ,
b111000100 "
b111000100 +
b111000100 .
b111000100 1
b111000100 5
1&
#1040000
0&
#1045000
b111001100 3
b1110010 0
b111001100 -
b111001100 !
b111001100 ,
b111001000 "
b111001000 +
b111001000 .
b111001000 1
b111001000 5
1&
