decode_execute/riscv_defines.vh

//opcode macros
//funct3 macros
//funct7 macros
//ALU operation macros
//writeback select macros
//immediate type macros
//FFT custom instruction macros
`ifndef RISCV_DEFINES_VH
`define RISCV_DEFINES_VH

// ============================================================
// Basic architectural parameters
// ============================================================
`define XLEN           32
`define REG_ADDR_W     5
`define INSTR_W        32
`define DATA_W         32
`define IMEM_DEPTH     1024
`define DMEM_DEPTH     1024
`define RESET_PC             0
// ============================================================
// RV32I opcodes
// ============================================================
`define OPCODE_OP      7'b0110011   // R-type
`define OPCODE_OP_IMM  7'b0010011   // I-type ALU
`define OPCODE_LOAD    7'b0000011   // LW
`define OPCODE_STORE   7'b0100011   // SW
`define OPCODE_BRANCH  7'b1100011   // BEQ/BNE
`define OPCODE_JAL     7'b1101111   // JAL

// ============================================================
// Custom opcode space for FFT instruction
// custom-0 opcode
// ============================================================
`define OPCODE_FFT     7'b0001011

// ============================================================
// funct3 values
// ============================================================
`define FUNCT3_ADD_SUB 3'b000
`define FUNCT3_XOR     3'b100
`define FUNCT3_OR      3'b110
`define FUNCT3_AND     3'b111

`define FUNCT3_ADDI    3'b000

`define FUNCT3_LW      3'b010
`define FUNCT3_SW      3'b010

`define FUNCT3_BEQ     3'b000
`define FUNCT3_BNE     3'b001

// ============================================================
// funct7 values
// ============================================================
`define FUNCT7_ADD     7'b0000000
`define FUNCT7_SUB     7'b0100000
`define FUNCT7_LOGIC   7'b0000000

// ============================================================
// FFT custom instruction fields
// Example: FFT_BLY rd, rs1, rs2
// ============================================================
`define FUNCT3_FFT_BLY 3'b000
`define FUNCT7_FFT_BLY 7'b0000001

// ============================================================
// ALU operation select
// ============================================================
`define ALU_ADD        4'd0
`define ALU_SUB        4'd1
`define ALU_AND        4'd2
`define ALU_OR         4'd3
`define ALU_XOR        4'd4
`define ALU_PASS       4'd5

// ============================================================
// Writeback select
// ============================================================
`define WB_ALU         2'd0
`define WB_MEM         2'd1
`define WB_PC4         2'd2
`define WB_FFT         2'd3

// ============================================================
// Immediate type select
// ============================================================
`define IMM_I          3'd0
`define IMM_S          3'd1
`define IMM_B          3'd2
`define IMM_J          3'd3
`define IMM_NONE       3'd4

`endif

fetch_stage/instr_mem.v
`include "riscv_defines.vh"
//`include "../riscv_defines.vh"



/*
------------------------------------------------------------------------------
File        : instr_mem.v
Module      : instr_mem
Purpose     : Synthesizable instruction ROM for baseline RV32I fetch stage

Functionality:
- Stores 32-bit instructions as fixed ROM contents
- Provides combinational instruction fetch using current PC
- Uses word-aligned addressing with pc_in[31:2]

Major inputs:
- pc_in         : Current Program Counter from fetch stage

Major outputs:
- instr_out     : 32-bit fetched instruction

Notes:
- Pure combinational ROM model
- No initial block, no $readmemh
- Suitable for stricter synthesizable RTL coding style
- Lower 2 bits of PC are ignored because instructions are 32-bit aligned
- Unused addresses return 32'h0000_0000
- Replace ROM contents below with your actual program instructions
------------------------------------------------------------------------------
*/

module instr_mem (
    input  [`XLEN-1:0] pc_in,
    output reg [31:0]  instr_out
);

    wire [`XLEN-1:0] word_addr;
    assign word_addr = pc_in >> 2;

//    always @(*) begin
//        case (word_addr)
//            32'd0: instr_out = 32'h00A00093; // addi x1, x0, 10
//            32'd1: instr_out = 32'h01400113; // addi x2, x0, 20
//            32'd2: instr_out = 32'h002081B3; // add  x3, x1, x2
//            32'd3: instr_out = 32'h40310233; // sub  x4, x2, x3
//            32'd4: instr_out = 32'h00302023; // sw   x3, 0(x0)
//            32'd5: instr_out = 32'h00002283; // lw   x5, 0(x0)
//            32'd6: instr_out = 32'h00328463; // beq  x5, x3, +8
//            32'd7: instr_out = 32'h00100313; // addi x6, x0, 1
//            32'd8: instr_out = 32'h0000006F; // jal  x0, 0
//            default: instr_out = 32'h00000000;
//        endcase
//    end
always @(*) begin
    case (word_addr)
        32'd0: instr_out = 32'h002081B3; // ADD  x3, x1, x2  (002081B3)
        32'd1: instr_out = 32'h402081B3; // SUB  x3, x1, x2  (402081B3)
        32'd2: instr_out = 32'h0020F1B3; // AND  x3, x1, x2  (0020F1B3)
        32'd3: instr_out = 32'h0020E1B3; // OR   x3, x1, x2  (0020E1B3)
        32'd4: instr_out = 32'h0020C1B3; // XOR  x3, x1, x2  (0020C1B3)
        32'd5: instr_out = 32'h00A02083; // LW   x1, 0(x0)  (00A02083)
        32'd6: instr_out = 32'h00302023; // SW   x3, 0(x0)  (00302023)
        32'd7: instr_out = 32'h00208463; // BEQ  x1, x2, +8 (00208463)
        32'd8: instr_out = 32'h00209463; // BNE  x1, x2, +8 (00209463)
        32'd9: instr_out = 32'h0000006F; // JAL  x0, 0      (0000006F)
        32'd10: instr_out = 32'h020000BB; // FFT  x0, x4, x4 (020000BB)
        default: instr_out = 32'h0000006F; 
    endcase
end


endmodule

fetch_stage/tb_instr_mem.v
`timescale 1ns/1ps
`include "riscv_defines.vh"

/*
------------------------------------------------------------------------------
File        : tb_instr_mem.v
Testbench   : tb_instr_mem
Purpose     : Self-checking testbench for instr_mem.v

What this TB verifies:
1. Correct instruction fetch at PC = 0
2. Correct instruction fetch at PC = 4
3. Correct instruction fetch at later word addresses
4. Word-aligned addressing using pc_in[31:2]
5. Unmapped/default addresses return 32'h0000_0000

DUT inputs driven by TB:
- pc_in         : Current Program Counter / fetch address

DUT outputs checked by TB:
- instr_out     : 32-bit fetched instruction

Pass/Fail method:
- TB applies directed PC values
- TB checks fetched instruction against expected ROM contents
- Prints PASS/FAIL messages using $display
- Dumps waveform file for GTKWave debug

Run command (Icarus Verilog):
- Compile : iverilog -o imem_tb instr_mem.v tb_instr_mem.v
- Run     : vvp imem_tb
- Waveform: gtkwave tb_instr_mem.vcd

Notes:
- Pure Verilog testbench, no SystemVerilog features used
- This TB assumes instr_mem.v is implemented as case-based ROM
- If ROM contents are changed in instr_mem.v, expected values here must match
------------------------------------------------------------------------------
*/

module tb_instr_mem;

    reg  [`XLEN-1:0] pc_in;
    wire [31:0]      instr_out;

    integer errors;

    instr_mem uut (
        .pc_in    (pc_in),
        .instr_out(instr_out)
    );

    task check_instr;
        input [31:0] expected_instr;
        input [127:0] test_name;
        begin
            #1;
            if (instr_out !== expected_instr) begin
                $display("FAIL : %s", test_name);
                $display("       pc_in=%h", pc_in);
                $display("       expected instr_out=%h", expected_instr);
                $display("       got      instr_out=%h", instr_out);
                errors = errors + 1;
            end
            else begin
                $display("PASS : %s  instr_out=%h", test_name, instr_out);
            end
        end
    endtask

    initial begin
        $dumpfile("tb_instr_mem.vcd");
        $dumpvars(0, tb_instr_mem);

        errors = 0;

        // ------------------------------------------------------
        // Test 1: Fetch instruction at word address 0
        // ------------------------------------------------------
        pc_in = 32'h0000_0000;
        check_instr(32'h00A00093, "FETCH_ADDR_0");

        // ------------------------------------------------------
        // Test 2: Fetch instruction at word address 1
        // ------------------------------------------------------
        pc_in = 32'h0000_0004;
        check_instr(32'h01400113, "FETCH_ADDR_1");

        // ------------------------------------------------------
        // Test 3: Fetch instruction at word address 2
        // ------------------------------------------------------
        pc_in = 32'h0000_0008;
        check_instr(32'h002081B3, "FETCH_ADDR_2");

        // ------------------------------------------------------
        // Test 4: Fetch instruction at word address 3
        // ------------------------------------------------------
        pc_in = 32'h0000_000C;
        check_instr(32'h40310233, "FETCH_ADDR_3");

        // ------------------------------------------------------
        // Test 5: Fetch instruction at word address 4
        // ------------------------------------------------------
        pc_in = 32'h0000_0010;
        check_instr(32'h00302023, "FETCH_ADDR_4");

        // ------------------------------------------------------
        // Test 6: Fetch instruction at word address 5
        // ------------------------------------------------------
        pc_in = 32'h0000_0014;
        check_instr(32'h00002283, "FETCH_ADDR_5");

        // ------------------------------------------------------
        // Test 7: Fetch instruction at word address 6
        // ------------------------------------------------------
        pc_in = 32'h0000_0018;
        check_instr(32'h00328463, "FETCH_ADDR_6");

        // ------------------------------------------------------
        // Test 8: Fetch instruction at word address 7
        // ------------------------------------------------------
        pc_in = 32'h0000_001C;
        check_instr(32'h00100313, "FETCH_ADDR_7");

        // ------------------------------------------------------
        // Test 9: Fetch instruction at word address 8
        // ------------------------------------------------------
        pc_in = 32'h0000_0020;
        check_instr(32'h0000006F, "FETCH_ADDR_8");

        // ------------------------------------------------------
        // Test 10: Unmapped address should return zero
        // ------------------------------------------------------
        pc_in = 32'h0000_0024;
        check_instr(32'h00000000, "FETCH_DEFAULT_ZERO");

        // ------------------------------------------------------
        // Test 11: Word alignment check
        // pc_in[31:2] is used, so 0x00000002 still maps to word 0
        // ------------------------------------------------------
        pc_in = 32'h0000_0002;
        check_instr(32'h00A00093, "WORD_ALIGN_ADDR_0");

        // ------------------------------------------------------
        // Test 12: Word alignment check
        // 0x00000006 maps to word 1
        // ------------------------------------------------------
        pc_in = 32'h0000_0006;
        check_instr(32'h01400113, "WORD_ALIGN_ADDR_1");

        if (errors == 0)
            $display("\nALL INSTR_MEM TESTS PASSED\n");
        else
            $display("\nINSTR_MEM TESTS FAILED : total errors = %0d\n", errors);

        #1000;$finish;
    end

endmodule

fetch_stage/tb_instr_mem.vcd
$date
	Wed Apr 22 21:11:56 2026
$end
$version
	Icarus Verilog
$end
$timescale
	1ps
$end
$scope module tb_instr_mem $end
$var wire 32 ! instr_out [31:0] $end
$var reg 32 " pc_in [31:0] $end
$var integer 32 # errors [31:0] $end
$scope module uut $end
$var wire 32 $ pc_in [31:0] $end
$var wire 32 % word_addr [31:0] $end
$var reg 32 & instr_out [31:0] $end
$upscope $end
$scope task check_instr $end
$var reg 32 ' expected_instr [31:0] $end
$var reg 128 ( test_name [127:0] $end
$upscope $end
$upscope $end
$enddefinitions $end
$comment Show the parameter values. $end
$dumpall
$end
#0
$dumpvars
b10001100100010101010100010000110100100001011111010000010100010001000100010100100101111100110000 (
b101000000000000010010011 '
b101000000000000010010011 &
b0 %
b0 $
b0 #
b0 "
b101000000000000010010011 !
$end
#1000
b1010000000000000100010011 !
b1010000000000000100010011 &
b1 %
b10001100100010101010100010000110100100001011111010000010100010001000100010100100101111100110001 (
b1010000000000000100010011 '
b100 "
b100 $
#2000
b1000001000000110110011 !
b1000001000000110110011 &
b10 %
b10001100100010101010100010000110100100001011111010000010100010001000100010100100101111100110010 (
b1000001000000110110011 '
b1000 "
b1000 $
#3000
b1000000001100010000001000110011 !
b1000000001100010000001000110011 &
b11 %
b10001100100010101010100010000110100100001011111010000010100010001000100010100100101111100110011 (
b1000000001100010000001000110011 '
b1100 "
b1100 $
#4000
b1100000010000000100011 !
b1100000010000000100011 &
b100 %
b10001100100010101010100010000110100100001011111010000010100010001000100010100100101111100110100 (
b1100000010000000100011 '
b10000 "
b10000 $
#5000
b10001010000011 !
b10001010000011 &
b101 %
b10001100100010101010100010000110100100001011111010000010100010001000100010100100101111100110101 (
b10001010000011 '
b10100 "
b10100 $
#6000
b1100101000010001100011 !
b1100101000010001100011 &
b110 %
b10001100100010101010100010000110100100001011111010000010100010001000100010100100101111100110110 (
b1100101000010001100011 '
b11000 "
b11000 $
#7000
b100000000001100010011 !
b100000000001100010011 &
b111 %
b10001100100010101010100010000110100100001011111010000010100010001000100010100100101111100110111 (
b100000000001100010011 '
b11100 "
b11100 $
#8000
b1101111 !
b1101111 &
b1000 %
b10001100100010101010100010000110100100001011111010000010100010001000100010100100101111100111000 (
b1101111 '
b100000 "
b100000 $
#9000
b0 !
b0 &
b1001 %
b1010100010000110100100001011111010001000100010101000110010000010101010101001100010101000101111101011010010001010101001001001111 (
b0 '
b100100 "
b100100 $
#10000
b101000000000000010010011 !
b101000000000000010010011 &
b0 %
b1001111010100100100010001011111010000010100110001001001010001110100111001011111010000010100010001000100010100100101111100110000 (
b101000000000000010010011 '
b10 "
b10 $
#11000
b1010000000000000100010011 !
b1010000000000000100010011 &
b1 %
b1001111010100100100010001011111010000010100110001001001010001110100111001011111010000010100010001000100010100100101111100110001 (
b1010000000000000100010011 '
b110 "
b110 $
