decode_execute/riscv_defines.vh

//opcode macros
//funct3 macros
//funct7 macros
//ALU operation macros
//writeback select macros
//immediate type macros
//FFT custom instruction macros
`ifndef RISCV_DEFINES_VH
`define RISCV_DEFINES_VH

// ============================================================
// Basic architectural parameters
// ============================================================
`define XLEN           32
`define REG_ADDR_W     5
`define INSTR_W        32
`define DATA_W         32
`define IMEM_DEPTH     1024
`define DMEM_DEPTH     1024
`define RESET_PC             0
// ============================================================
// RV32I opcodes
// ============================================================
`define OPCODE_OP      7'b0110011   // R-type
`define OPCODE_OP_IMM  7'b0010011   // I-type ALU
`define OPCODE_LOAD    7'b0000011   // LW
`define OPCODE_STORE   7'b0100011   // SW
`define OPCODE_BRANCH  7'b1100011   // BEQ/BNE
`define OPCODE_JAL     7'b1101111   // JAL

// ============================================================
// Custom opcode space for FFT instruction
// custom-0 opcode
// ============================================================
`define OPCODE_FFT     7'b0001011

// ============================================================
// funct3 values
// ============================================================
`define FUNCT3_ADD_SUB 3'b000
`define FUNCT3_XOR     3'b100
`define FUNCT3_OR      3'b110
`define FUNCT3_AND     3'b111

`define FUNCT3_ADDI    3'b000

`define FUNCT3_LW      3'b010
`define FUNCT3_SW      3'b010

`define FUNCT3_BEQ     3'b000
`define FUNCT3_BNE     3'b001

// ============================================================
// funct7 values
// ============================================================
`define FUNCT7_ADD     7'b0000000
`define FUNCT7_SUB     7'b0100000
`define FUNCT7_LOGIC   7'b0000000

// ============================================================
// FFT custom instruction fields
// Example: FFT_BLY rd, rs1, rs2
// ============================================================
`define FUNCT3_FFT_BLY 3'b000
`define FUNCT7_FFT_BLY 7'b0000001

// ============================================================
// ALU operation select
// ============================================================
`define ALU_ADD        4'd0
`define ALU_SUB        4'd1
`define ALU_AND        4'd2
`define ALU_OR         4'd3
`define ALU_XOR        4'd4
`define ALU_PASS       4'd5

// ============================================================
// Writeback select
// ============================================================
`define WB_ALU         2'd0
`define WB_MEM         2'd1
`define WB_PC4         2'd2
`define WB_FFT         2'd3

// ============================================================
// Immediate type select
// ============================================================
`define IMM_I          3'd0
`define IMM_S          3'd1
`define IMM_B          3'd2
`define IMM_J          3'd3
`define IMM_NONE       3'd4

`endif

fetch_stage/pc_reg.v
//`include "../riscv_defines.vh"
`include "riscv_defines.vh"

/*
------------------------------------------------------------------------------
File        : pc_reg.v
Module      : pc_reg
Purpose     : Program Counter register for baseline RV32I datapath

Functionality:
- Holds the current Program Counter (PC)
- Updates PC on every clock edge
- Supports reset, stall, and next-PC loading
- Used by instruction fetch stage

Major inputs:
- clk        : Clock input
- rst_n      : Active-low reset
- stall      : Holds current PC when asserted
- next_pc    : Next PC value to be loaded

Major outputs:
- pc_out     : Current PC value

Notes:
- Sequential logic block
- On reset, PC is initialized to RESET_PC
- If stall = 1, current PC is retained
- Otherwise, PC is updated with next_pc
- Written in Verilog-only style for Icarus compatibility

Run note:
- This is an RTL module, so it is compiled together with its testbench
------------------------------------------------------------------------------
*/

//module pc_reg (
//    input                  clk,
//    input                  rst_n,
//    input                  stall,
//    input  [31:0]     next_pc,
//    output reg [31:0] pc_out
//);
//
//    always @(posedge clk or negedge rst_n) begin
//        if (!rst_n)
//          //  pc_out <= `RESET_PC;
//pc_out <= 32'h0000_1000; 
//        else if (stall)
//            pc_out <= pc_out;
//        else
//            pc_out <= next_pc;
//    end
//
//endmodule
`timescale 1ns/1ps

module pc_reg (
    input  wire        clk,
    input  wire        rst_n,
    input  wire        stall,
    input  wire [31:0] next_pc,
    output reg  [31:0] pc_out
);

    always @(posedge clk or negedge rst_n) begin
        if (!rst_n)
            pc_out <= 32'h0000_1000;
        else if (!stall)
            pc_out <= next_pc;
    end

endmodule

fetch_stage/tb_pc_reg.v
`timescale 1ns/1ps
`include "riscv_defines.vh"

/*
Checked
------------------------------------------------------------------------------
File        : tb_pc_reg.v
Testbench   : tb_pc_reg
Purpose     : Self-checking testbench for pc_reg.v

What this TB verifies:
1. PC resets to RESET_PC
2. PC updates to next_pc on clock edge
3. PC holds value when stall is asserted
4. PC resumes updating after stall is deasserted

DUT inputs driven by TB:
- clk        : Clock input
- rst_n      : Active-low reset
- stall      : Hold current PC when asserted
- next_pc    : Next PC value to load

DUT outputs checked by TB:
- pc_out     : Current Program Counter value

Pass/Fail method:
- TB drives reset, next_pc, and stall
- TB checks pc_out after relevant clock edges
- Prints PASS/FAIL messages using $display
- Dumps waveform file for GTKWave debug

Run command (Icarus Verilog):
- Compile : iverilog -o pc_tb pc_reg.v tb_pc_reg.v
- Run     : vvp pc_tb
- Waveform: gtkwave tb_pc_reg.vcd

Notes:
- Pure Verilog testbench, no SystemVerilog features used
- This TB checks only the PC register, not next-PC selection logic
------------------------------------------------------------------------------
*/

module tb_pc_reg;

    reg              clk;
    reg              rst_n;
    reg              stall;
    reg  [`XLEN-1:0] next_pc;

    wire [`XLEN-1:0] pc_out;

    integer errors;

    pc_reg uut (
        .clk     (clk),
        .rst_n   (rst_n),
        .stall   (stall),
        .next_pc (next_pc),
        .pc_out  (pc_out)
    );

    // Clock generation
    initial begin
        clk = 1'b0;
        forever #5 clk = ~clk;
    end

    task check_pc;
        input [`XLEN-1:0] expected_pc;
        input [127:0]     test_name;
        begin
            #1;
            if (pc_out !== expected_pc) begin
                $display("FAIL : %s", test_name);
                $display("       rst_n=%b stall=%b next_pc=%h", rst_n, stall, next_pc);
                $display("       expected pc_out=%h", expected_pc);
                $display("       got      pc_out=%h", pc_out);
                errors = errors + 1;
            end
            else begin
                $display("PASS : %s  pc_out=%h", test_name, pc_out);
            end
        end
    endtask

    initial begin
        $dumpfile("tb_pc_reg.vcd");
        $dumpvars(0, tb_pc_reg);

        errors = 0;

        // Initialize
        rst_n   = 1'b0;
        stall   = 1'b0;
        next_pc = 32'h0000_0000;

        // ------------------------------------------------------
        // Test 1: Reset should force PC to RESET_PC
        // ------------------------------------------------------
        #2;
        check_pc(`RESET_PC, "ASYNC_RESET_VALUE");

        // Release reset
        #8;
        rst_n = 1'b1;

        // ------------------------------------------------------
        // Test 2: Normal PC update
        // ------------------------------------------------------
        next_pc = 32'h0000_0004;
        @(posedge clk);
        check_pc(32'h0000_0004, "NORMAL_UPDATE_1");

        next_pc = 32'h0000_0008;
        @(posedge clk);
        check_pc(32'h0000_0008, "NORMAL_UPDATE_2");

        // ------------------------------------------------------
        // Test 3: Stall should hold PC
        // ------------------------------------------------------
        stall   = 1'b1;
        next_pc = 32'h0000_0010;
        @(posedge clk);
        check_pc(32'h0000_0008, "STALL_HOLDS_PC");

        // ------------------------------------------------------
        // Test 4: Remove stall, PC should update again
        // ------------------------------------------------------
        stall   = 1'b0;
        next_pc = 32'h0000_0010;
        @(posedge clk);
        check_pc(32'h0000_0010, "UPDATE_AFTER_STALL");

        // ------------------------------------------------------
        // Test 5: Another normal update
        // ------------------------------------------------------
        next_pc = 32'h0000_0020;
        @(posedge clk);
        check_pc(32'h0000_0020, "NORMAL_UPDATE_3");

        // ------------------------------------------------------
        // Test 6: Assert reset again during operation
        // ------------------------------------------------------
        #2;
        rst_n = 1'b0;
        check_pc(`RESET_PC, "RESET_DURING_OPERATION");

        if (errors == 0)
            $display("\nALL PC_REG TESTS PASSED\n");
        else
            $display("\nPC_REG TESTS FAILED : total errors = %0d\n", errors);
       #1000;
        $finish;
    end

endmodule

fetch_stage/tb_pc_reg.vcd
$date
	Wed Apr 22 21:00:51 2026
$end
$version
	Icarus Verilog
$end
$timescale
	1ps
$end
$scope module tb_pc_reg $end
$var wire 32 ! pc_out [31:0] $end
$var reg 1 " clk $end
$var reg 32 # next_pc [31:0] $end
$var reg 1 $ rst_n $end
$var reg 1 % stall $end
$var integer 32 & errors [31:0] $end
$scope module uut $end
$var wire 1 " clk $end
$var wire 32 ' next_pc [31:0] $end
$var wire 1 $ rst_n $end
$var wire 1 % stall $end
$var reg 32 ( pc_out [31:0] $end
$upscope $end
$scope task check_pc $end
$var reg 32 ) expected_pc [31:0] $end
$var reg 128 * test_name [127:0] $end
$upscope $end
$upscope $end
$enddefinitions $end
$comment Show the parameter values. $end
$dumpall
$end
#0
$dumpvars
bx *
bx )
b0 (
b0 '
b0 &
0%
0$
b0 #
0"
b0 !
$end
#2000
b1010011010110010100111001000011010111110101001001000101010100110100010101010100010111110101011001000001010011000101010101000101 *
b0 )
#5000
1"
#10000
0"
#11000
b100 #
b100 '
1$
#15000
b100 !
b100 (
b10011100100111101010010010011010100000101001100010111110101010101010000010001000100000101010100010001010101111100110001 *
b100 )
1"
#16000
b1000 #
b1000 '
#20000
0"
#25000
b1000 !
b1000 (
b10011100100111101010010010011010100000101001100010111110101010101010000010001000100000101010100010001010101111100110010 *
b1000 )
1"
#26000
b10000 #
b10000 '
1%
#30000
0"
#35000
b101001101010100010000010100110001001100010111110100100001001111010011000100010001010011010111110101000001000011 *
1"
#36000
0%
#40000
0"
#45000
b10000 !
b10000 (
b1000100010000010101010001000101010111110100000101000110010101000100010101010010010111110101001101010100010000010100110001001100 *
b10000 )
1"
#46000
b100000 #
b100000 '
#50000
0"
#55000
b100000 !
b100000 (
b10011100100111101010010010011010100000101001100010111110101010101010000010001000100000101010100010001010101111100110011 *
b100000 )
1"
#58000
b0 !
b0 (
b1000100010101010101001001001001010011100100011101011111010011110101000001000101010100100100000101010100010010010100111101001110 *
b0 )
0$
