decode_execute/riscv_defines.vh

//opcode macros
//funct3 macros
//funct7 macros
//ALU operation macros
//writeback select macros
//immediate type macros
//FFT custom instruction macros
`ifndef RISCV_DEFINES_VH
`define RISCV_DEFINES_VH

// ============================================================
// Basic architectural parameters
// ============================================================
`define XLEN           32
`define REG_ADDR_W     5
`define INSTR_W        32
`define DATA_W         32
`define IMEM_DEPTH     1024
`define DMEM_DEPTH     1024
`define RESET_PC             0
// ============================================================
// RV32I opcodes
// ============================================================
`define OPCODE_OP      7'b0110011   // R-type
`define OPCODE_OP_IMM  7'b0010011   // I-type ALU
`define OPCODE_LOAD    7'b0000011   // LW
`define OPCODE_STORE   7'b0100011   // SW
`define OPCODE_BRANCH  7'b1100011   // BEQ/BNE
`define OPCODE_JAL     7'b1101111   // JAL

// ============================================================
// Custom opcode space for FFT instruction
// custom-0 opcode
// ============================================================
`define OPCODE_FFT     7'b0001011

// ============================================================
// funct3 values
// ============================================================
`define FUNCT3_ADD_SUB 3'b000
`define FUNCT3_XOR     3'b100
`define FUNCT3_OR      3'b110
`define FUNCT3_AND     3'b111

`define FUNCT3_ADDI    3'b000

`define FUNCT3_LW      3'b010
`define FUNCT3_SW      3'b010

`define FUNCT3_BEQ     3'b000
`define FUNCT3_BNE     3'b001

// ============================================================
// funct7 values
// ============================================================
`define FUNCT7_ADD     7'b0000000
`define FUNCT7_SUB     7'b0100000
`define FUNCT7_LOGIC   7'b0000000

// ============================================================
// FFT custom instruction fields
// Example: FFT_BLY rd, rs1, rs2
// ============================================================
`define FUNCT3_FFT_BLY 3'b000
`define FUNCT7_FFT_BLY 7'b0000001

// ============================================================
// ALU operation select
// ============================================================
`define ALU_ADD        4'd0
`define ALU_SUB        4'd1
`define ALU_AND        4'd2
`define ALU_OR         4'd3
`define ALU_XOR        4'd4
`define ALU_PASS       4'd5

// ============================================================
// Writeback select
// ============================================================
`define WB_ALU         2'd0
`define WB_MEM         2'd1
`define WB_PC4         2'd2
`define WB_FFT         2'd3

// ============================================================
// Immediate type select
// ============================================================
`define IMM_I          3'd0
`define IMM_S          3'd1
`define IMM_B          3'd2
`define IMM_J          3'd3
`define IMM_NONE       3'd4

`endif

fetch_stage/instr_mem.v
`include "riscv_defines.vh"
//`include "../riscv_defines.vh"



/*
------------------------------------------------------------------------------
File        : instr_mem.v
Module      : instr_mem
Purpose     : Synthesizable instruction ROM for baseline RV32I fetch stage

Functionality:
- Stores 32-bit instructions as fixed ROM contents
- Provides combinational instruction fetch using current PC
- Uses word-aligned addressing with pc_in[31:2]

Major inputs:
- pc_in         : Current Program Counter from fetch stage

Major outputs:
- instr_out     : 32-bit fetched instruction

Notes:
- Pure combinational ROM model
- No initial block, no $readmemh
- Suitable for stricter synthesizable RTL coding style
- Lower 2 bits of PC are ignored because instructions are 32-bit aligned
- Unused addresses return 32'h0000_0000
- Replace ROM contents below with your actual program instructions
------------------------------------------------------------------------------
*/

module instr_mem (
    input  [`XLEN-1:0] pc_in,
    output reg [31:0]  instr_out
);

    wire [`XLEN-1:0] word_addr;
    assign word_addr = pc_in >> 2;

//    always @(*) begin
//        case (word_addr)
//            32'd0: instr_out = 32'h00A00093; // addi x1, x0, 10
//            32'd1: instr_out = 32'h01400113; // addi x2, x0, 20
//            32'd2: instr_out = 32'h002081B3; // add  x3, x1, x2
//            32'd3: instr_out = 32'h40310233; // sub  x4, x2, x3
//            32'd4: instr_out = 32'h00302023; // sw   x3, 0(x0)
//            32'd5: instr_out = 32'h00002283; // lw   x5, 0(x0)
//            32'd6: instr_out = 32'h00328463; // beq  x5, x3, +8
//            32'd7: instr_out = 32'h00100313; // addi x6, x0, 1
//            32'd8: instr_out = 32'h0000006F; // jal  x0, 0
//            default: instr_out = 32'h00000000;
//        endcase
//    end
always @(*) begin
    case (word_addr)
        32'd0: instr_out = 32'h002081B3; // ADD  x3, x1, x2  (002081B3)
        32'd1: instr_out = 32'h402081B3; // SUB  x3, x1, x2  (402081B3)
        32'd2: instr_out = 32'h0020F1B3; // AND  x3, x1, x2  (0020F1B3)
        32'd3: instr_out = 32'h0020E1B3; // OR   x3, x1, x2  (0020E1B3)
        32'd4: instr_out = 32'h0020C1B3; // XOR  x3, x1, x2  (0020C1B3)
        32'd5: instr_out = 32'h00A02083; // LW   x1, 0(x0)  (00A02083)
        32'd6: instr_out = 32'h00302023; // SW   x3, 0(x0)  (00302023)
        32'd7: instr_out = 32'h00208463; // BEQ  x1, x2, +8 (00208463)
        32'd8: instr_out = 32'h00209463; // BNE  x1, x2, +8 (00209463)
        32'd9: instr_out = 32'h0000006F; // JAL  x0, 0      (0000006F)
        32'd10: instr_out = 32'h020000BB; // FFT  x0, x4, x4 (020000BB)
        default: instr_out = 32'h0000006F; 
    endcase
end


endmodule

fetch_stage/pc_reg.v
//`include "../riscv_defines.vh"
`include "riscv_defines.vh"

/*
------------------------------------------------------------------------------
File        : pc_reg.v
Module      : pc_reg
Purpose     : Program Counter register for baseline RV32I datapath

Functionality:
- Holds the current Program Counter (PC)
- Updates PC on every clock edge
- Supports reset, stall, and next-PC loading
- Used by instruction fetch stage

Major inputs:
- clk        : Clock input
- rst_n      : Active-low reset
- stall      : Holds current PC when asserted
- next_pc    : Next PC value to be loaded

Major outputs:
- pc_out     : Current PC value

Notes:
- Sequential logic block
- On reset, PC is initialized to RESET_PC
- If stall = 1, current PC is retained
- Otherwise, PC is updated with next_pc
- Written in Verilog-only style for Icarus compatibility

Run note:
- This is an RTL module, so it is compiled together with its testbench
------------------------------------------------------------------------------
*/

//module pc_reg (
//    input                  clk,
//    input                  rst_n,
//    input                  stall,
//    input  [31:0]     next_pc,
//    output reg [31:0] pc_out
//);
//
//    always @(posedge clk or negedge rst_n) begin
//        if (!rst_n)
//          //  pc_out <= `RESET_PC;
//pc_out <= 32'h0000_1000; 
//        else if (stall)
//            pc_out <= pc_out;
//        else
//            pc_out <= next_pc;
//    end
//
//endmodule
`timescale 1ns/1ps

module pc_reg (
    input  wire        clk,
    input  wire        rst_n,
    input  wire        stall,
    input  wire [31:0] next_pc,
    output reg  [31:0] pc_out
);

    always @(posedge clk or negedge rst_n) begin
        if (!rst_n)
            pc_out <= 32'h0000_1000;
        else if (!stall)
            pc_out <= next_pc;
    end

endmodule

fetch_stage/fetch_stage.v
//`include "pc_reg.v"
//`include "instr_mem.v"
`timescale 1ns/1ps

module fetch_stage (
    input  wire        clk,
    input  wire        rst_n,
    input  wire        stall,
    input  wire        branch_taken,
    input  wire [31:0] branch_target,
    output wire [31:0] pc_out,
    output wire [31:0] instr_out,
    output wire [31:0] pc_plus4_out
);

    wire [31:0] pc_current;
    wire [31:0] pc_next;

    assign pc_next     = branch_taken ? branch_target : (pc_current + 32'd4);
    assign pc_plus4_out = pc_current + 32'd4;

    pc_reg u_pc_reg (
        .clk     (clk),
        .rst_n   (rst_n),
        .stall   (stall),
        .next_pc (pc_next),
        .pc_out  (pc_current)
    );

    instr_mem u_instr_mem (
        .pc_in     (pc_current),
        .instr_out (instr_out)
    );

    assign pc_out = pc_current;

endmodule

sim/fetch_stage/tb_fetch_stage_v2.v
//    iverilog -I ../../ -o fetch_tb ../../fetch_stage/fetch_stage.v ../../fetch_stage/pc_reg.v ../../fetch_stage/instr_mem.v tb_fetch_stage_v2.v
//vvp fetch_tb
`timescale 1ns/1ps
`include "riscv_defines.vh"

`timescale 1ns/1ps
`include "riscv_defines.vh"

module tb_fetch_stage_v2;

    reg         clk;
    reg         rst_n;
    reg         stall;
    reg         branch_taken;
    reg [31:0]  branch_target;

    wire [31:0] pc_out;
    wire [31:0] instr_out;
    wire [31:0] pc_plus4_out;

    integer pass_count;
    integer fail_count;

    fetch_stage uut (
        .clk           (clk),
        .rst_n         (rst_n),
        .stall         (stall),
        .branch_taken  (branch_taken),
        .branch_target (branch_target),
        .pc_out        (pc_out),
        .instr_out     (instr_out),
        .pc_plus4_out  (pc_plus4_out)
    );

    always #5 clk = ~clk;

    task check_equal_32;
        input [255:0] test_name;
        input [31:0]  actual;
        input [31:0]  expected;
        begin
            if (actual !== expected) begin
                $display("FAIL: %0s | expected=%h actual=%h time=%0t",
                         test_name, expected, actual, $time);
                fail_count = fail_count + 1;
            end
            else begin
                $display("PASS: %0s | value=%h time=%0t",
                         test_name, actual, $time);
                pass_count = pass_count + 1;
            end
        end
    endtask

    task sample_and_check_pc;
        input [255:0] test_name;
        input [31:0]  expected_pc;
        input [31:0]  expected_pc_plus4;
        begin
            @(negedge clk);
            #1;
            check_equal_32({test_name, " PC"}, pc_out, expected_pc);
            check_equal_32({test_name, " PC_PLUS4"}, pc_plus4_out, expected_pc_plus4);
        end
    endtask

    initial begin
        $dumpfile("tb_fetch_stage_v2.vcd");
        $dumpvars(0, tb_fetch_stage_v2);

        clk           = 1'b0;
        rst_n         = 1'b0;
        stall         = 1'b0;
        branch_taken  = 1'b0;
        branch_target = 32'h0000_0000;
        pass_count    = 0;
        fail_count    = 0;

        $display("========================================");
        $display("Starting FETCH STAGE self-checking TB");
        $display("========================================");

        // Hold reset for two cycles

        // Test 1: reset release value
        sample_and_check_pc("RESET_VALUE", 32'h0000_1000, 32'h0000_1004);
        repeat (2) @(negedge clk);
        rst_n = 1'b1;

        // Test 2: sequential increment
        sample_and_check_pc("PC_INC_1", 32'h0000_1004, 32'h0000_1008);
        sample_and_check_pc("PC_INC_2", 32'h0000_1008, 32'h0000_100C);

        // Test 3: stall should hold PC
        stall = 1'b1;
        sample_and_check_pc("STALL_HOLD", 32'h0000_1008, 32'h0000_100C);
        stall = 1'b0;

        // Test 4: after stall release, increment resumes
        sample_and_check_pc("STALL_RELEASE", 32'h0000_100C, 32'h0000_1010);

        // Test 5: branch
        branch_target = 32'h0000_2000;
        branch_taken  = 1'b1;
        sample_and_check_pc("BRANCH_TAKEN", 32'h0000_2000, 32'h0000_2004);
        branch_taken  = 1'b0;

        // Test 6: continue sequentially after branch
        sample_and_check_pc("POST_BRANCH_INC", 32'h0000_2004, 32'h0000_2008);

        $display("========================================");
        $display("Simulation done: PASS=%0d FAIL=%0d", pass_count, fail_count);
        $display("========================================");

        if (fail_count == 0)
            $display("FINAL RESULT: TEST PASSED");
        else
            $display("FINAL RESULT: TEST FAILED");

        #10;
        $finish;
    end

    initial begin
        $monitor("T=%0t clk=%b rst_n=%b stall=%b branch_taken=%b branch_target=%h pc_out=%h pc_plus4_out=%h instr_out=%h",
                 $time, clk, rst_n, stall, branch_taken, branch_target, pc_out, pc_plus4_out, instr_out);
    end

endmodule

sim/fetch_stage/tb_fetch_stage_v2.vcd
$date
	Sun May 03 19:24:09 2026
$end
$version
	Icarus Verilog
$end
$timescale
	1ps
$end
$scope module tb_fetch_stage_v2 $end
$var wire 32 ! pc_plus4_out [31:0] $end
$var wire 32 " pc_out [31:0] $end
$var wire 32 # instr_out [31:0] $end
$var reg 1 $ branch_taken $end
$var reg 32 % branch_target [31:0] $end
$var reg 1 & clk $end
$var reg 1 ' rst_n $end
$var reg 1 ( stall $end
$var integer 32 ) fail_count [31:0] $end
$var integer 32 * pass_count [31:0] $end
$scope module uut $end
$var wire 1 $ branch_taken $end
$var wire 32 + branch_target [31:0] $end
$var wire 1 & clk $end
$var wire 32 , pc_out [31:0] $end
$var wire 1 ' rst_n $end
$var wire 1 ( stall $end
$var wire 32 - pc_plus4_out [31:0] $end
$var wire 32 . pc_next [31:0] $end
$var wire 32 / pc_current [31:0] $end
$var wire 32 0 instr_out [31:0] $end
$scope module u_instr_mem $end
$var wire 32 1 word_addr [31:0] $end
$var wire 32 2 pc_in [31:0] $end
$var reg 32 3 instr_out [31:0] $end
$upscope $end
$scope module u_pc_reg $end
$var wire 1 & clk $end
$var wire 32 4 next_pc [31:0] $end
$var wire 1 ' rst_n $end
$var wire 1 5 stall $end
$var reg 32 6 pc_out [31:0] $end
$upscope $end
$upscope $end
$scope task check_equal_32 $end
$var reg 32 7 actual [31:0] $end
$var reg 32 8 expected [31:0] $end
$var reg 256 9 test_name [255:0] $end
$upscope $end
$scope task sample_and_check_pc $end
$var reg 32 : expected_pc [31:0] $end
$var reg 32 ; expected_pc_plus4 [31:0] $end
$var reg 256 < test_name [255:0] $end
$upscope $end
$upscope $end
$enddefinitions $end
$comment Show the parameter values. $end
$dumpall
$end
#0
$dumpvars
b101001001000101010100110100010101010100010111110101011001000001010011000101010101000101 <
b1000000000100 ;
b1000000000000 :
bx 9
bx 8
bx 7
b1000000000000 6
z5
b1000000000100 4
b0 3
b1000000000000 2
b10000000000 1
b0 0
b1000000000000 /
b1000000000100 .
b1000000000100 -
b1000000000000 ,
b0 +
b0 *
b0 )
0(
0'
0&
b0 %
0$
b0 #
b1000000000000 "
b1000000000100 !
$end
#5000
1&
#10000
0&
#11000
b10 *
b1000000000100 8
b1000000000100 7
b101001001000101010100110100010101010100010111110101011001000001010011000101010101000101001000000101000001000011010111110101000001001100010101010101001100110100 9
#15000
1&
#20000
0&
#25000
1&
#30000
b1000000001000 ;
b1000000000100 :
b101000001000011010111110100100101001110010000110101111100110001 <
1'
0&
#35000
b1000000001000 4
b10000000001 1
b1000000001000 .
b1000000001000 !
b1000000001000 -
b1000000000100 "
b1000000000100 ,
b1000000000100 /
b1000000000100 2
b1000000000100 6
1&
#40000
0&
#41000
b1000000001100 ;
b1000000001000 :
b101000001000011010111110100100101001110010000110101111100110010 <
b1000000001000 8
b1000000001000 7
b100 *
b101000001000011010111110100100101001110010000110101111100110001001000000101000001000011010111110101000001001100010101010101001100110100 9
#45000
b1000000001100 4
b10000000010 1
b1000000001100 .
b1000000001100 !
b1000000001100 -
b1000000001000 "
b1000000001000 ,
b1000000001000 /
b1000000001000 2
b1000000001000 6
1&
#50000
0&
#51000
b1000000001000 4
b1010011010101000100000101001100010011000101111101001000010011110100110001000100 <
1(
b1000000001100 8
b1000000001100 7
b110 *
b101000001000011010111110100100101001110010000110101111100110010001000000101000001000011010111110101000001001100010101010101001100110100 9
#55000
1&
#60000
0&
#61000
b1000000001100 4
b1000000010000 ;
b1000000001100 :
b1010011010101000100000101001100010011000101111101010010010001010100110001000101010000010101001101000101 <
0(
b1000 *
b1000000001100 8
b1000000001100 7
b1010011010101000100000101001100010011000101111101001000010011110100110001000100001000000101000001000011010111110101000001001100010101010101001100110100 9
#65000
b1000000010000 4
b10000000011 1
b1000000010000 .
b1000000010000 !
b1000000010000 -
b1000000001100 "
b1000000001100 ,
b1000000001100 /
b1000000001100 2
b1000000001100 6
1&
#70000
0&
#71000
b10000000000000 4
b10000000000000 .
b10000000000100 ;
b10000000000000 :
b10000100101001001000001010011100100001101001000010111110101010001000001010010110100010101001110 <
1$
b10000000000000 %
b10000000000000 +
b1000000010000 8
b1000000010000 7
b1010 *
b1010011010101000100000101001100010011000101111101010010010001010100110001000101010000010101001101000101001000000101000001000011010111110101000001001100010101010101001100110100 9
#75000
b100000000000 1
b10000000000100 !
b10000000000100 -
b10000000000000 "
b10000000000000 ,
b10000000000000 /
b10000000000000 2
b10000000000000 6
1&
#80000
0&
#81000
b10000000000100 4
b10000000000100 .
b10000000001000 ;
b10000000000100 :
b10100000100111101010011010101000101111101000010010100100100000101001110010000110100100001011111010010010100111001000011 <
0$
b1100 *
b10000000000100 8
b10000000000100 7
b10000100101001001000001010011100100001101001000010111110101010001000001010010110100010101001110001000000101000001000011010111110101000001001100010101010101001100110100 9
#85000
b10000000001000 4
b100000000001 1
b10000000001000 .
b10000000001000 !
b10000000001000 -
b10000000000100 "
b10000000000100 ,
b10000000000100 /
b10000000000100 2
b10000000000100 6
1&
#90000
0&
#91000
b10000000001000 8
b10000000001000 7
b1110 *
b10100000100111101010011010101000101111101000010010100100100000101001110010000110100100001011111010010010100111001000011001000000101000001000011010111110101000001001100010101010101001100110100 9
#95000
b10000000001100 4
b100000000010 1
b10000000001100 .
b10000000001100 !
b10000000001100 -
b10000000001000 "
b10000000001000 ,
b10000000001000 /
b10000000001000 2
b10000000001000 6
1&
